{
"meta":{"test_sets":[],"test_metrics":[],"learn_metrics":[{"best_value":"Min","name":"Logloss"}],"launch_mode":"Train","parameters":"","iteration_count":1000,"learn_sets":["learn"],"name":"experiment"},
"iterations":[
{"learn":[0.6787797881],"iteration":0,"passed_time":0.001562186037,"remaining_time":1.560623851},
{"learn":[0.6661995368],"iteration":1,"passed_time":0.002691354596,"remaining_time":1.342985943},
{"learn":[0.6537200183],"iteration":2,"passed_time":0.004184902101,"remaining_time":1.390782465},
{"learn":[0.6400454141],"iteration":3,"passed_time":0.005564547155,"remaining_time":1.385572242},
{"learn":[0.6266718919],"iteration":4,"passed_time":0.006603692895,"remaining_time":1.314134886},
{"learn":[0.6113242793],"iteration":5,"passed_time":0.007609487199,"remaining_time":1.260638379},
{"learn":[0.5980602978],"iteration":6,"passed_time":0.008610491244,"remaining_time":1.221459686},
{"learn":[0.5842177228],"iteration":7,"passed_time":0.009725078572,"remaining_time":1.205909743},
{"learn":[0.5701780862],"iteration":8,"passed_time":0.01075164737,"remaining_time":1.183875839},
{"learn":[0.5587360413],"iteration":9,"passed_time":0.01181750032,"remaining_time":1.169932531},
{"learn":[0.5462429388],"iteration":10,"passed_time":0.01292732745,"remaining_time":1.162284259},
{"learn":[0.5334553292],"iteration":11,"passed_time":0.01396896853,"remaining_time":1.150111743},
{"learn":[0.5224075938],"iteration":12,"passed_time":0.01502219443,"remaining_time":1.140531223},
{"learn":[0.5113376214],"iteration":13,"passed_time":0.01608486055,"remaining_time":1.13283375},
{"learn":[0.5007081071],"iteration":14,"passed_time":0.01717992606,"remaining_time":1.128148478},
{"learn":[0.4905463118],"iteration":15,"passed_time":0.01827664512,"remaining_time":1.124013675},
{"learn":[0.4806459939],"iteration":16,"passed_time":0.01935766054,"remaining_time":1.119328254},
{"learn":[0.4707926929],"iteration":17,"passed_time":0.02037445841,"remaining_time":1.111539898},
{"learn":[0.4604711145],"iteration":18,"passed_time":0.02139243882,"remaining_time":1.104525394},
{"learn":[0.4502434769],"iteration":19,"passed_time":0.02243582364,"remaining_time":1.099355358},
{"learn":[0.4398840927],"iteration":20,"passed_time":0.02345717126,"remaining_time":1.093550984},
{"learn":[0.4316012375],"iteration":21,"passed_time":0.02457198908,"remaining_time":1.092336605},
{"learn":[0.4238976269],"iteration":22,"passed_time":0.02586672378,"remaining_time":1.098773441},
{"learn":[0.4152034977],"iteration":23,"passed_time":0.02723000378,"remaining_time":1.107353487},
{"learn":[0.4083287929],"iteration":24,"passed_time":0.02881981414,"remaining_time":1.123972751},
{"learn":[0.3993655569],"iteration":25,"passed_time":0.02983354544,"remaining_time":1.11761051},
{"learn":[0.3912419265],"iteration":26,"passed_time":0.03085298898,"remaining_time":1.111850307},
{"learn":[0.3844787474],"iteration":27,"passed_time":0.03188243394,"remaining_time":1.106775921},
{"learn":[0.3781945764],"iteration":28,"passed_time":0.03273574164,"remaining_time":1.096082936},
{"learn":[0.3718041521],"iteration":29,"passed_time":0.03382268977,"remaining_time":1.093600302},
{"learn":[0.3652166351],"iteration":30,"passed_time":0.03511389387,"remaining_time":1.09759236},
{"learn":[0.3585584067],"iteration":31,"passed_time":0.03623049035,"remaining_time":1.095972333},
{"learn":[0.3521797366],"iteration":32,"passed_time":0.03739362682,"remaining_time":1.09574658},
{"learn":[0.3454004924],"iteration":33,"passed_time":0.03843375466,"remaining_time":1.091970794},
{"learn":[0.33984375],"iteration":34,"passed_time":0.03964283924,"remaining_time":1.093009711},
{"learn":[0.3343098958],"iteration":35,"passed_time":0.04121444029,"remaining_time":1.103631123},
{"learn":[0.3305691355],"iteration":36,"passed_time":0.04233024022,"remaining_time":1.101730306},
{"learn":[0.3243438907],"iteration":37,"passed_time":0.04386554869,"remaining_time":1.110490996},
{"learn":[0.3187934441],"iteration":38,"passed_time":0.04518345666,"remaining_time":1.113366714},
{"learn":[0.3132693593],"iteration":39,"passed_time":0.04616403696,"remaining_time":1.107936887},
{"learn":[0.3083364595],"iteration":40,"passed_time":0.04742369501,"remaining_time":1.109251793},
{"learn":[0.3046797776],"iteration":41,"passed_time":0.04873540972,"remaining_time":1.111631488},
{"learn":[0.3005213544],"iteration":42,"passed_time":0.05029705459,"remaining_time":1.119401889},
{"learn":[0.2962382557],"iteration":43,"passed_time":0.05179356997,"remaining_time":1.12533302},
{"learn":[0.2912472981],"iteration":44,"passed_time":0.05297640985,"remaining_time":1.124277142},
{"learn":[0.2865170114],"iteration":45,"passed_time":0.05428522683,"remaining_time":1.1258284},
{"learn":[0.2818810068],"iteration":46,"passed_time":0.05541383419,"remaining_time":1.123603915},
{"learn":[0.2767378954],"iteration":47,"passed_time":0.05656518511,"remaining_time":1.121876171},
{"learn":[0.2716587966],"iteration":48,"passed_time":0.05778342961,"remaining_time":1.121470236},
{"learn":[0.2674918446],"iteration":49,"passed_time":0.05904756544,"remaining_time":1.121903743},
{"learn":[0.2633119288],"iteration":50,"passed_time":0.06017758765,"remaining_time":1.119775111},
{"learn":[0.2601658271],"iteration":51,"passed_time":0.06158367418,"remaining_time":1.122717752},
{"learn":[0.2562415115],"iteration":52,"passed_time":0.06280854105,"remaining_time":1.122258271},
{"learn":[0.2517300272],"iteration":53,"passed_time":0.06419839464,"remaining_time":1.124660765},
{"learn":[0.2471617877],"iteration":54,"passed_time":0.06540821595,"remaining_time":1.123832074},
{"learn":[0.2430786195],"iteration":55,"passed_time":0.06665983193,"remaining_time":1.12369431},
{"learn":[0.2409252384],"iteration":56,"passed_time":0.06779171114,"remaining_time":1.121536554},
{"learn":[0.2375759962],"iteration":57,"passed_time":0.06883085202,"remaining_time":1.117907976},
{"learn":[0.235233555],"iteration":58,"passed_time":0.06954579821,"remaining_time":1.109196544},
{"learn":[0.2322931522],"iteration":59,"passed_time":0.07060714666,"remaining_time":1.106178631},
{"learn":[0.2288085348],"iteration":60,"passed_time":0.07167405185,"remaining_time":1.103310405},
{"learn":[0.2258747225],"iteration":61,"passed_time":0.07268320335,"remaining_time":1.099626528},
{"learn":[0.2223930669],"iteration":62,"passed_time":0.07383809185,"remaining_time":1.098195112},
{"learn":[0.2190388005],"iteration":63,"passed_time":0.07502998992,"remaining_time":1.097313603},
{"learn":[0.2159097098],"iteration":64,"passed_time":0.0762017497,"remaining_time":1.096132861},
{"learn":[0.2128168742],"iteration":65,"passed_time":0.07726370916,"remaining_time":1.093398551},
{"learn":[0.2103751888],"iteration":66,"passed_time":0.0784283288,"remaining_time":1.092143743},
{"learn":[0.2071093738],"iteration":67,"passed_time":0.07960780997,"remaining_time":1.091095278},
{"learn":[0.2045617918],"iteration":68,"passed_time":0.08072903151,"remaining_time":1.089256932},
{"learn":[0.201261691],"iteration":69,"passed_time":0.08184166981,"remaining_time":1.087325042},
{"learn":[0.1979347787],"iteration":70,"passed_time":0.08294532372,"remaining_time":1.085298672},
{"learn":[0.1951446068],"iteration":71,"passed_time":0.08400055877,"remaining_time":1.082673869},
{"learn":[0.192639126],"iteration":72,"passed_time":0.08503556079,"remaining_time":1.079835135},
{"learn":[0.1896802701],"iteration":73,"passed_time":0.08612365622,"remaining_time":1.077709536},
{"learn":[0.1871005733],"iteration":74,"passed_time":0.0872377525,"remaining_time":1.075932281},
{"learn":[0.1842684707],"iteration":75,"passed_time":0.08832075217,"remaining_time":1.073794408},
{"learn":[0.1821884993],"iteration":76,"passed_time":0.08951273041,"remaining_time":1.072990262},
{"learn":[0.1800106018],"iteration":77,"passed_time":0.09073700267,"remaining_time":1.072557903},
{"learn":[0.1777790504],"iteration":78,"passed_time":0.09187253486,"remaining_time":1.071070944},
{"learn":[0.1758072706],"iteration":79,"passed_time":0.09303024455,"remaining_time":1.069847812},
{"learn":[0.173995491],"iteration":80,"passed_time":0.09421573375,"remaining_time":1.068941473},
{"learn":[0.171621028],"iteration":81,"passed_time":0.09524910712,"remaining_time":1.06632537},
{"learn":[0.1694180248],"iteration":82,"passed_time":0.09648875717,"remaining_time":1.066026389},
{"learn":[0.1676470284],"iteration":83,"passed_time":0.09772590367,"remaining_time":1.065677711},
{"learn":[0.1659411299],"iteration":84,"passed_time":0.09890686316,"remaining_time":1.064703292},
{"learn":[0.1642673927],"iteration":85,"passed_time":0.1000114542,"remaining_time":1.062912432},
{"learn":[0.1622044323],"iteration":86,"passed_time":0.1011151731,"remaining_time":1.061128196},
{"learn":[0.1604706369],"iteration":87,"passed_time":0.1022045698,"remaining_time":1.059210996},
{"learn":[0.1585793844],"iteration":88,"passed_time":0.103221037,"remaining_time":1.056565896},
{"learn":[0.1567307294],"iteration":89,"passed_time":0.1042755824,"remaining_time":1.054342},
{"learn":[0.1554100378],"iteration":90,"passed_time":0.1055131683,"remaining_time":1.053972198},
{"learn":[0.1536095162],"iteration":91,"passed_time":0.1066843268,"remaining_time":1.052927921},
{"learn":[0.1517665832],"iteration":92,"passed_time":0.1078854246,"remaining_time":1.052172904},
{"learn":[0.1503536721],"iteration":93,"passed_time":0.1090669453,"remaining_time":1.051219707},
{"learn":[0.1491338063],"iteration":94,"passed_time":0.1101392921,"remaining_time":1.049221678},
{"learn":[0.147666559],"iteration":95,"passed_time":0.1114088763,"remaining_time":1.049100252},
{"learn":[0.1459557758],"iteration":96,"passed_time":0.1124858582,"remaining_time":1.047162165},
{"learn":[0.145014414],"iteration":97,"passed_time":0.113169703,"remaining_time":1.041623184},
{"learn":[0.1433393277],"iteration":98,"passed_time":0.1143030553,"remaining_time":1.040273261},
{"learn":[0.1419350074],"iteration":99,"passed_time":0.1153823923,"remaining_time":1.038441531},
{"learn":[0.1407524667],"iteration":100,"passed_time":0.1164787406,"remaining_time":1.036776117},
{"learn":[0.1394693948],"iteration":101,"passed_time":0.117433771,"remaining_time":1.033877709},
{"learn":[0.1382044971],"iteration":102,"passed_time":0.1184932752,"remaining_time":1.031926872},
{"learn":[0.1370644608],"iteration":103,"passed_time":0.1195434248,"remaining_time":1.029912583},
{"learn":[0.1356426177],"iteration":104,"passed_time":0.1208148629,"remaining_time":1.029802879},
{"learn":[0.1342897027],"iteration":105,"passed_time":0.1220002868,"remaining_time":1.028945815},
{"learn":[0.1329096352],"iteration":106,"passed_time":0.1231704432,"remaining_time":1.027955194},
{"learn":[0.1318325725],"iteration":107,"passed_time":0.1242569154,"remaining_time":1.026270079},
{"learn":[0.1303701323],"iteration":108,"passed_time":0.1253961957,"remaining_time":1.025027618},
{"learn":[0.1289631913],"iteration":109,"passed_time":0.1265062332,"remaining_time":1.023550433},
{"learn":[0.127404399],"iteration":110,"passed_time":0.1275792464,"remaining_time":1.021783334},
{"learn":[0.1263083404],"iteration":111,"passed_time":0.1287893434,"remaining_time":1.021115509},
{"learn":[0.1253291417],"iteration":112,"passed_time":0.1298836874,"remaining_time":1.019529475},
{"learn":[0.1242487217],"iteration":113,"passed_time":0.130934964,"remaining_time":1.017617351},
{"learn":[0.1234429522],"iteration":114,"passed_time":0.1319371906,"remaining_time":1.015342728},
{"learn":[0.1224079132],"iteration":115,"passed_time":0.132986742,"remaining_time":1.013450689},
{"learn":[0.1213164756],"iteration":116,"passed_time":0.1340204427,"remaining_time":1.011453427},
{"learn":[0.1204956411],"iteration":117,"passed_time":0.1350961319,"remaining_time":1.009786342},
{"learn":[0.119484537],"iteration":118,"passed_time":0.1363179838,"remaining_time":1.009211292},
{"learn":[0.1185510372],"iteration":119,"passed_time":0.1374861511,"remaining_time":1.008231774},
{"learn":[0.1175392275],"iteration":120,"passed_time":0.1386104492,"remaining_time":1.006930453},
{"learn":[0.1167492207],"iteration":121,"passed_time":0.1396920908,"remaining_time":1.005325047},
{"learn":[0.1159001095],"iteration":122,"passed_time":0.1408190546,"remaining_time":1.004051308},
{"learn":[0.1147555375],"iteration":123,"passed_time":0.1420033865,"remaining_time":1.003185214},
{"learn":[0.1140688842],"iteration":124,"passed_time":0.1431400912,"remaining_time":1.001980638},
{"learn":[0.1131327172],"iteration":125,"passed_time":0.1443043549,"remaining_time":1.000968303},
{"learn":[0.1123267926],"iteration":126,"passed_time":0.1455361029,"remaining_time":1.000417463},
{"learn":[0.1113659308],"iteration":127,"passed_time":0.1465664698,"remaining_time":0.9984840757},
{"learn":[0.1104305857],"iteration":128,"passed_time":0.1475671432,"remaining_time":0.9963641992},
{"learn":[0.1095424513],"iteration":129,"passed_time":0.1483756549,"remaining_time":0.9929755368},
{"learn":[0.1086745223],"iteration":130,"passed_time":0.1494299583,"remaining_time":0.9912567461},
{"learn":[0.1078935871],"iteration":131,"passed_time":0.1504417053,"remaining_time":0.9892681835},
{"learn":[0.1070497172],"iteration":132,"passed_time":0.151549468,"remaining_time":0.9879202165},
{"learn":[0.1061661573],"iteration":133,"passed_time":0.1528018305,"remaining_time":0.9875103372},
{"learn":[0.1053141462],"iteration":134,"passed_time":0.154093532,"remaining_time":0.9873400384},
{"learn":[0.104547299],"iteration":135,"passed_time":0.1554021902,"remaining_time":0.9872609728},
{"learn":[0.1036173037],"iteration":136,"passed_time":0.1566352613,"remaining_time":0.9866878137},
{"learn":[0.1028291811],"iteration":137,"passed_time":0.1576795079,"remaining_time":0.984925622},
{"learn":[0.1021532974],"iteration":138,"passed_time":0.1586249029,"remaining_time":0.9825614487},
{"learn":[0.1012762892],"iteration":139,"passed_time":0.1599944563,"remaining_time":0.9828230888},
{"learn":[0.1006262554],"iteration":140,"passed_time":0.1610691983,"remaining_time":0.9812655414},
{"learn":[0.09987691554],"iteration":141,"passed_time":0.162269379,"remaining_time":0.9804727263},
{"learn":[0.09916586217],"iteration":142,"passed_time":0.1633410091,"remaining_time":0.9789038099},
{"learn":[0.09839729371],"iteration":143,"passed_time":0.1644812748,"remaining_time":0.9777498001},
{"learn":[0.09772065015],"iteration":144,"passed_time":0.1655858473,"remaining_time":0.9763855135},
{"learn":[0.0969900736],"iteration":145,"passed_time":0.1665990776,"remaining_time":0.9744904947},
{"learn":[0.09635208874],"iteration":146,"passed_time":0.1678307308,"remaining_time":0.9738749208},
{"learn":[0.09556805215],"iteration":147,"passed_time":0.168998492,"remaining_time":0.9728832107},
{"learn":[0.09506139523],"iteration":148,"passed_time":0.1701855946,"remaining_time":0.9719996043},
{"learn":[0.09424118104],"iteration":149,"passed_time":0.1713449779,"remaining_time":0.9709548749},
{"learn":[0.09374647993],"iteration":150,"passed_time":0.1724956674,"remaining_time":0.969859746},
{"learn":[0.09319092975],"iteration":151,"passed_time":0.173922223,"remaining_time":0.9703029281},
{"learn":[0.09253315034],"iteration":152,"passed_time":0.1750361589,"remaining_time":0.9689910234},
{"learn":[0.09188392298],"iteration":153,"passed_time":0.1761269103,"remaining_time":0.9675543255},
{"learn":[0.09100186728],"iteration":154,"passed_time":0.1771563553,"remaining_time":0.9657878723},
{"learn":[0.09076182823],"iteration":155,"passed_time":0.1777917811,"remaining_time":0.9618991236},
{"learn":[0.09018792563],"iteration":156,"passed_time":0.1788373106,"remaining_time":0.9602538395},
{"learn":[0.08963082476],"iteration":157,"passed_time":0.1798620955,"remaining_time":0.9585055977},
{"learn":[0.08910644345],"iteration":158,"passed_time":0.1808610953,"remaining_time":0.95663007},
{"learn":[0.08866544274],"iteration":159,"passed_time":0.1818789153,"remaining_time":0.9548643056},
{"learn":[0.08820200354],"iteration":160,"passed_time":0.18311123,"remaining_time":0.9542256022},
{"learn":[0.0876969981],"iteration":161,"passed_time":0.1842609025,"remaining_time":0.9531520757},
{"learn":[0.08705053872],"iteration":162,"passed_time":0.1854158563,"remaining_time":0.9521047342},
{"learn":[0.08640486244],"iteration":163,"passed_time":0.1865068931,"remaining_time":0.9507302601},
{"learn":[0.08594081848],"iteration":164,"passed_time":0.1876807957,"remaining_time":0.9497785721},
{"learn":[0.08534916823],"iteration":165,"passed_time":0.1909049433,"remaining_time":0.9591248356},
{"learn":[0.08470962493],"iteration":166,"passed_time":0.2052817268,"remaining_time":1.02395017},
{"learn":[0.08406643751],"iteration":167,"passed_time":0.2223560081,"remaining_time":1.101191659},
{"learn":[0.08356117621],"iteration":168,"passed_time":0.235057784,"remaining_time":1.155816678},
{"learn":[0.08312495937],"iteration":169,"passed_time":0.2521994997,"remaining_time":1.231326969},
{"learn":[0.08276875814],"iteration":170,"passed_time":0.2666090182,"remaining_time":1.292508047},
{"learn":[0.0823801785],"iteration":171,"passed_time":0.2822913682,"remaining_time":1.358937517},
{"learn":[0.08180871049],"iteration":172,"passed_time":0.2963702136,"remaining_time":1.416752408},
{"learn":[0.08143256738],"iteration":173,"passed_time":0.3079636603,"remaining_time":1.461942434},
{"learn":[0.08094700759],"iteration":174,"passed_time":0.3093436012,"remaining_time":1.45833412},
{"learn":[0.08055031009],"iteration":175,"passed_time":0.3107089219,"remaining_time":1.45468268},
{"learn":[0.07989812091],"iteration":176,"passed_time":0.312103509,"remaining_time":1.451193152},
{"learn":[0.07941805832],"iteration":177,"passed_time":0.3133615135,"remaining_time":1.447096427},
{"learn":[0.0789444621],"iteration":178,"passed_time":0.3145402683,"remaining_time":1.442667934},
{"learn":[0.07851212974],"iteration":179,"passed_time":0.3154595922,"remaining_time":1.437093698},
{"learn":[0.07804380587],"iteration":180,"passed_time":0.3166372546,"remaining_time":1.432739843},
{"learn":[0.07764856602],"iteration":181,"passed_time":0.3178856786,"remaining_time":1.428738929},
{"learn":[0.07717416345],"iteration":182,"passed_time":0.318987153,"remaining_time":1.424112044},
{"learn":[0.07673303868],"iteration":183,"passed_time":0.3200810108,"remaining_time":1.4194897},
{"learn":[0.07638384656],"iteration":184,"passed_time":0.3211926819,"remaining_time":1.414983977},
{"learn":[0.07605441024],"iteration":185,"passed_time":0.3226168073,"remaining_time":1.411882157},
{"learn":[0.07568159336],"iteration":186,"passed_time":0.3238419764,"remaining_time":1.407933298},
{"learn":[0.07533506068],"iteration":187,"passed_time":0.3250093115,"remaining_time":1.403763622},
{"learn":[0.0748770489],"iteration":188,"passed_time":0.3262512015,"remaining_time":1.399945632},
{"learn":[0.0744538346],"iteration":189,"passed_time":0.3274867479,"remaining_time":1.396127715},
{"learn":[0.07401346191],"iteration":190,"passed_time":0.3286551855,"remaining_time":1.392052592},
{"learn":[0.07363385301],"iteration":191,"passed_time":0.3299030382,"remaining_time":1.388341953},
{"learn":[0.07331130175],"iteration":192,"passed_time":0.3311119776,"remaining_time":1.384494124},
{"learn":[0.07287807775],"iteration":193,"passed_time":0.3323900603,"remaining_time":1.380960766},
{"learn":[0.07248934304],"iteration":194,"passed_time":0.3334710606,"remaining_time":1.376636942},
{"learn":[0.0720645703],"iteration":195,"passed_time":0.3346233587,"remaining_time":1.372638675},
{"learn":[0.07168821785],"iteration":196,"passed_time":0.335640292,"remaining_time":1.368117535},
{"learn":[0.07134717461],"iteration":197,"passed_time":0.3366461765,"remaining_time":1.363587038},
{"learn":[0.07092340981],"iteration":198,"passed_time":0.3377248769,"remaining_time":1.359385057},
{"learn":[0.07068179681],"iteration":199,"passed_time":0.3389378498,"remaining_time":1.355751399},
{"learn":[0.07035798174],"iteration":200,"passed_time":0.3398349264,"remaining_time":1.350886101},
{"learn":[0.06993186765],"iteration":201,"passed_time":0.341099976,"remaining_time":1.347513767},
{"learn":[0.06960014405],"iteration":202,"passed_time":0.3423728272,"remaining_time":1.344192824},
{"learn":[0.06929962034],"iteration":203,"passed_time":0.3436742997,"remaining_time":1.34100364},
{"learn":[0.06901853453],"iteration":204,"passed_time":0.3449172018,"remaining_time":1.337605734},
{"learn":[0.06870866791],"iteration":205,"passed_time":0.3463276024,"remaining_time":1.334874351},
{"learn":[0.06836333701],"iteration":206,"passed_time":0.3475989993,"remaining_time":1.331623219},
{"learn":[0.06812486416],"iteration":207,"passed_time":0.3487265243,"remaining_time":1.327843304},
{"learn":[0.06782612374],"iteration":208,"passed_time":0.3498612047,"remaining_time":1.324115851},
{"learn":[0.06748644511],"iteration":209,"passed_time":0.3509532537,"remaining_time":1.320252716},
{"learn":[0.06732880197],"iteration":210,"passed_time":0.3516894354,"remaining_time":1.31508514},
{"learn":[0.06700908072],"iteration":211,"passed_time":0.3527137794,"remaining_time":1.311030463},
{"learn":[0.06671581423],"iteration":212,"passed_time":0.353892905,"remaining_time":1.307576133},
{"learn":[0.06633743038],"iteration":213,"passed_time":0.3550414451,"remaining_time":1.304030728},
{"learn":[0.06596844371],"iteration":214,"passed_time":0.3562304518,"remaining_time":1.30065537},
{"learn":[0.06559436302],"iteration":215,"passed_time":0.3573027737,"remaining_time":1.296876734},
{"learn":[0.0652298811],"iteration":216,"passed_time":0.3585076192,"remaining_time":1.293601225},
{"learn":[0.06490857039],"iteration":217,"passed_time":0.3597252925,"remaining_time":1.290390728},
{"learn":[0.06467633131],"iteration":218,"passed_time":0.3609210537,"remaining_time":1.287120287},
{"learn":[0.06437243485],"iteration":219,"passed_time":0.3620200076,"remaining_time":1.283525481},
{"learn":[0.06410890672],"iteration":220,"passed_time":0.363224307,"remaining_time":1.280324594},
{"learn":[0.0638997109],"iteration":221,"passed_time":0.3642731484,"remaining_time":1.276596889},
{"learn":[0.06368016809],"iteration":222,"passed_time":0.3653156313,"remaining_time":1.272871056},
{"learn":[0.06335237937],"iteration":223,"passed_time":0.3663391636,"remaining_time":1.269103531},
{"learn":[0.06310927771],"iteration":224,"passed_time":0.3674011683,"remaining_time":1.265492913},
{"learn":[0.06282917271],"iteration":225,"passed_time":0.3685001722,"remaining_time":1.262031563},
{"learn":[0.06255679402],"iteration":226,"passed_time":0.3697594446,"remaining_time":1.259136787},
{"learn":[0.06232358188],"iteration":227,"passed_time":0.3709003583,"remaining_time":1.255855599},
{"learn":[0.06210772972],"iteration":228,"passed_time":0.3720240952,"remaining_time":1.252535273},
{"learn":[0.06180010385],"iteration":229,"passed_time":0.3731115044,"remaining_time":1.249112428},
{"learn":[0.06158650018],"iteration":230,"passed_time":0.3741485055,"remaining_time":1.245541995},
{"learn":[0.06129506739],"iteration":231,"passed_time":0.3754783588,"remaining_time":1.242962843},
{"learn":[0.06094894564],"iteration":232,"passed_time":0.376628768,"remaining_time":1.239803713},
{"learn":[0.06072613088],"iteration":233,"passed_time":0.3778139164,"remaining_time":1.23677547},
{"learn":[0.06050862336],"iteration":234,"passed_time":0.3788951724,"remaining_time":1.23342471},
{"learn":[0.06010426932],"iteration":235,"passed_time":0.37993989,"remaining_time":1.229974898},
{"learn":[0.05986683931],"iteration":236,"passed_time":0.3809686936,"remaining_time":1.226494149},
{"learn":[0.05959482115],"iteration":237,"passed_time":0.381964246,"remaining_time":1.222927544},
{"learn":[0.05935935664],"iteration":238,"passed_time":0.3829682665,"remaining_time":1.219409418},
{"learn":[0.05912225227],"iteration":239,"passed_time":0.3839716055,"remaining_time":1.215910084},
{"learn":[0.05886061986],"iteration":240,"passed_time":0.3851718712,"remaining_time":1.213051661},
{"learn":[0.05866148026],"iteration":241,"passed_time":0.386371611,"remaining_time":1.210205294},
{"learn":[0.05842838442],"iteration":242,"passed_time":0.3875428095,"remaining_time":1.207283567},
{"learn":[0.05826800044],"iteration":243,"passed_time":0.3887244553,"remaining_time":1.204408558},
{"learn":[0.05808957805],"iteration":244,"passed_time":0.3898489691,"remaining_time":1.201371313},
{"learn":[0.05784011469],"iteration":245,"passed_time":0.391295693,"remaining_time":1.199337205},
{"learn":[0.0576089921],"iteration":246,"passed_time":0.3925514976,"remaining_time":1.196725821},
{"learn":[0.0574181642],"iteration":247,"passed_time":0.3935994222,"remaining_time":1.193495022},
{"learn":[0.05712235458],"iteration":248,"passed_time":0.3947567261,"remaining_time":1.190611652},
{"learn":[0.05687039848],"iteration":249,"passed_time":0.395785254,"remaining_time":1.187355762},
{"learn":[0.0565184035],"iteration":250,"passed_time":0.3969005428,"remaining_time":1.18437652},
{"learn":[0.0563573876],"iteration":251,"passed_time":0.3981538424,"remaining_time":1.181821723},
{"learn":[0.05615627475],"iteration":252,"passed_time":0.3992448942,"remaining_time":1.178798166},
{"learn":[0.05590110097],"iteration":253,"passed_time":0.4003941509,"remaining_time":1.175960774},
{"learn":[0.05567601832],"iteration":254,"passed_time":0.4017043071,"remaining_time":1.173606701},
{"learn":[0.05544629911],"iteration":255,"passed_time":0.403065758,"remaining_time":1.171409859},
{"learn":[0.05525664973],"iteration":256,"passed_time":0.4042406445,"remaining_time":1.168680151},
{"learn":[0.05505968885],"iteration":257,"passed_time":0.4055285983,"remaining_time":1.166287674},
{"learn":[0.05485178009],"iteration":258,"passed_time":0.4067468577,"remaining_time":1.16370433},
{"learn":[0.05468921351],"iteration":259,"passed_time":0.4078658144,"remaining_time":1.160848856},
{"learn":[0.05452176614],"iteration":260,"passed_time":0.4089415084,"remaining_time":1.157884194},
{"learn":[0.05433678046],"iteration":261,"passed_time":0.4191722416,"remaining_time":1.18072181},
{"learn":[0.05412822816],"iteration":262,"passed_time":0.4339343468,"remaining_time":1.216006135},
{"learn":[0.05393353129],"iteration":263,"passed_time":0.4501297405,"remaining_time":1.254907155},
{"learn":[0.05379163928],"iteration":264,"passed_time":0.4653301281,"remaining_time":1.290632619},
{"learn":[0.05363584534],"iteration":265,"passed_time":0.4805983361,"remaining_time":1.326162326},
{"learn":[0.0534654439],"iteration":266,"passed_time":0.4954163663,"remaining_time":1.360075642},
{"learn":[0.05329849274],"iteration":267,"passed_time":0.5096872715,"remaining_time":1.392130906},
{"learn":[0.05316227238],"iteration":268,"passed_time":0.5110857569,"remaining_time":1.388861295},
{"learn":[0.05293012635],"iteration":269,"passed_time":0.5123035004,"remaining_time":1.385116871},
{"learn":[0.0527870752],"iteration":270,"passed_time":0.5134838486,"remaining_time":1.3812905},
{"learn":[0.05260600113],"iteration":271,"passed_time":0.514583629,"remaining_time":1.377267948},
{"learn":[0.05243787533],"iteration":272,"passed_time":0.5156965929,"remaining_time":1.373301916},
{"learn":[0.05228827252],"iteration":273,"passed_time":0.5168315137,"remaining_time":1.369414887},
{"learn":[0.05215851854],"iteration":274,"passed_time":0.5180628411,"remaining_time":1.365802036},
{"learn":[0.05194839229],"iteration":275,"passed_time":0.5192124234,"remaining_time":1.361992009},
{"learn":[0.05179120661],"iteration":276,"passed_time":0.5205589858,"remaining_time":1.358715331},
{"learn":[0.05166489516],"iteration":277,"passed_time":0.5217057921,"remaining_time":1.354933748},
{"learn":[0.05137956046],"iteration":278,"passed_time":0.5227789325,"remaining_time":1.350980682},
{"learn":[0.05120371997],"iteration":279,"passed_time":0.5239522939,"remaining_time":1.347305899},
{"learn":[0.05100213028],"iteration":280,"passed_time":0.525207404,"remaining_time":1.343858091},
{"learn":[0.05085073254],"iteration":281,"passed_time":0.526491785,"remaining_time":1.34050036},
{"learn":[0.05072134685],"iteration":282,"passed_time":0.5277049936,"remaining_time":1.336976963},
{"learn":[0.0505360898],"iteration":283,"passed_time":0.5403327509,"remaining_time":1.362247358},
{"learn":[0.05035748908],"iteration":284,"passed_time":0.5559384968,"remaining_time":1.394722895},
{"learn":[0.05014345123],"iteration":285,"passed_time":0.5697138202,"remaining_time":1.422292544},
{"learn":[0.0499701151],"iteration":286,"passed_time":0.5845813267,"remaining_time":1.452287407},
{"learn":[0.04980259407],"iteration":287,"passed_time":0.5997058867,"remaining_time":1.48260622},
{"learn":[0.04963111102],"iteration":288,"passed_time":0.6146591265,"remaining_time":1.512189062},
{"learn":[0.04946404744],"iteration":289,"passed_time":0.6286843904,"remaining_time":1.539192818},
{"learn":[0.04929080436],"iteration":290,"passed_time":0.6441165597,"remaining_time":1.569342408},
{"learn":[0.04912301971],"iteration":291,"passed_time":0.6596379482,"remaining_time":1.599396121},
{"learn":[0.04895765413],"iteration":292,"passed_time":0.6609399369,"remaining_time":1.594827766},
{"learn":[0.04871107892],"iteration":293,"passed_time":0.6623355179,"remaining_time":1.59050638},
{"learn":[0.04860460855],"iteration":294,"passed_time":0.6639604331,"remaining_time":1.5867529},
{"learn":[0.04845690533],"iteration":295,"passed_time":0.6652364013,"remaining_time":1.582183873},
{"learn":[0.04835140414],"iteration":296,"passed_time":0.6664976476,"remaining_time":1.577602176},
{"learn":[0.04825185373],"iteration":297,"passed_time":0.66765194,"remaining_time":1.572790812},
{"learn":[0.04804623612],"iteration":298,"passed_time":0.6687940663,"remaining_time":1.567975386},
{"learn":[0.04789442357],"iteration":299,"passed_time":0.6700146057,"remaining_time":1.563367413},
{"learn":[0.04772943016],"iteration":300,"passed_time":0.6712062982,"remaining_time":1.558714958},
{"learn":[0.0476411455],"iteration":301,"passed_time":0.6723254702,"remaining_time":1.553917809},
{"learn":[0.04750879024],"iteration":302,"passed_time":0.6734765308,"remaining_time":1.54921829},
{"learn":[0.04736938709],"iteration":303,"passed_time":0.6745583178,"remaining_time":1.544383517},
{"learn":[0.04725294191],"iteration":304,"passed_time":0.6758281878,"remaining_time":1.540001936},
{"learn":[0.04711997024],"iteration":305,"passed_time":0.6771209367,"remaining_time":1.535692582},
{"learn":[0.046964909],"iteration":306,"passed_time":0.6783104093,"remaining_time":1.531169751},
{"learn":[0.04677841528],"iteration":307,"passed_time":0.6794968004,"remaining_time":1.526661642},
{"learn":[0.04665643025],"iteration":308,"passed_time":0.6807236782,"remaining_time":1.522265572},
{"learn":[0.04653074683],"iteration":309,"passed_time":0.6818433565,"remaining_time":1.517651342},
{"learn":[0.04639772865],"iteration":310,"passed_time":0.6830392179,"remaining_time":1.513228364},
{"learn":[0.04625070386],"iteration":311,"passed_time":0.684095285,"remaining_time":1.508517808},
{"learn":[0.04608395429],"iteration":312,"passed_time":0.6852059038,"remaining_time":1.503950338},
{"learn":[0.04591530901],"iteration":313,"passed_time":0.6863620751,"remaining_time":1.499504406},
{"learn":[0.04575475057],"iteration":314,"passed_time":0.6876027276,"remaining_time":1.495263074},
{"learn":[0.04559471161],"iteration":315,"passed_time":0.6887619705,"remaining_time":1.490864519},
{"learn":[0.04550626026],"iteration":316,"passed_time":0.6898787574,"remaining_time":1.486394925},
{"learn":[0.04527408321],"iteration":317,"passed_time":0.6909922877,"remaining_time":1.481939435},
{"learn":[0.04514547674],"iteration":318,"passed_time":0.6922084425,"remaining_time":1.477723979},
{"learn":[0.04498772505],"iteration":319,"passed_time":0.6934307855,"remaining_time":1.473540419},
{"learn":[0.04487317171],"iteration":320,"passed_time":0.6945988225,"remaining_time":1.469260438},
{"learn":[0.04475174881],"iteration":321,"passed_time":0.696216327,"remaining_time":1.465946179},
{"learn":[0.04456444484],"iteration":322,"passed_time":0.6975764584,"remaining_time":1.462102979},
{"learn":[0.04434931375],"iteration":323,"passed_time":0.6987706062,"remaining_time":1.457928796},
{"learn":[0.04420377375],"iteration":324,"passed_time":0.6999343655,"remaining_time":1.453709836},
{"learn":[0.04403151148],"iteration":325,"passed_time":0.700962217,"remaining_time":1.449228633},
{"learn":[0.0439313718],"iteration":326,"passed_time":0.7021034949,"remaining_time":1.445001994},
{"learn":[0.04378958834],"iteration":327,"passed_time":0.7034256067,"remaining_time":1.441164658},
{"learn":[0.04361579089],"iteration":328,"passed_time":0.7045871011,"remaining_time":1.43701503},
{"learn":[0.04350404817],"iteration":329,"passed_time":0.7057402663,"remaining_time":1.432866601},
{"learn":[0.04333474384],"iteration":330,"passed_time":0.7067335037,"remaining_time":1.428413033},
{"learn":[0.04323886856],"iteration":331,"passed_time":0.7078353437,"remaining_time":1.424198824},
{"learn":[0.04311865907],"iteration":332,"passed_time":0.7088703153,"remaining_time":1.41986937},
{"learn":[0.04299370835],"iteration":333,"passed_time":0.7098767811,"remaining_time":1.415502803},
{"learn":[0.0428886181],"iteration":334,"passed_time":0.7110041309,"remaining_time":1.41139626},
{"learn":[0.04276588874],"iteration":335,"passed_time":0.7121362157,"remaining_time":1.407316807},
{"learn":[0.04255197494],"iteration":336,"passed_time":0.7133009854,"remaining_time":1.403319149},
{"learn":[0.04244516342],"iteration":337,"passed_time":0.7142819015,"remaining_time":1.398978162},
{"learn":[0.0423184294],"iteration":338,"passed_time":0.7153933622,"remaining_time":1.394911541},
{"learn":[0.04223182725],"iteration":339,"passed_time":0.7164395378,"remaining_time":1.390735573},
{"learn":[0.04212527934],"iteration":340,"passed_time":0.7175636707,"remaining_time":1.386728619},
{"learn":[0.04195979359],"iteration":341,"passed_time":0.7187610803,"remaining_time":1.382879505},
{"learn":[0.04182718246],"iteration":342,"passed_time":0.7199275239,"remaining_time":1.37898654},
{"learn":[0.0417119817],"iteration":343,"passed_time":0.7211469606,"remaining_time":1.375210483},
{"learn":[0.04162622467],"iteration":344,"passed_time":0.7221925301,"remaining_time":1.371119151},
{"learn":[0.04150002177],"iteration":345,"passed_time":0.723275565,"remaining_time":1.367116241},
{"learn":[0.04139412903],"iteration":346,"passed_time":0.7243604636,"remaining_time":1.363133668},
{"learn":[0.04126806182],"iteration":347,"passed_time":0.7254079372,"remaining_time":1.359097629},
{"learn":[0.04116762363],"iteration":348,"passed_time":0.726507768,"remaining_time":1.355176381},
{"learn":[0.04109458613],"iteration":349,"passed_time":0.7276284032,"remaining_time":1.351309892},
{"learn":[0.04094249446],"iteration":350,"passed_time":0.7288018116,"remaining_time":1.347556626},
{"learn":[0.04081992018],"iteration":351,"passed_time":0.7299219709,"remaining_time":1.343719992},
{"learn":[0.04069398089],"iteration":352,"passed_time":0.7310050304,"remaining_time":1.33983075},
{"learn":[0.04054529686],"iteration":353,"passed_time":0.732319446,"remaining_time":1.336379554},
{"learn":[0.0403921546],"iteration":354,"passed_time":0.7336051347,"remaining_time":1.332888202},
{"learn":[0.04024363339],"iteration":355,"passed_time":0.7347837443,"remaining_time":1.329215537},
{"learn":[0.04015575967],"iteration":356,"passed_time":0.7484846602,"remaining_time":1.348111027},
{"learn":[0.0399852303],"iteration":357,"passed_time":0.7624443753,"remaining_time":1.367288517},
{"learn":[0.0398625087],"iteration":358,"passed_time":0.7783917146,"remaining_time":1.389830332},
{"learn":[0.03974861827],"iteration":359,"passed_time":0.7926015154,"remaining_time":1.409069361},
{"learn":[0.03968488104],"iteration":360,"passed_time":0.8065360817,"remaining_time":1.42763589},
{"learn":[0.03955254128],"iteration":361,"passed_time":0.8203746273,"remaining_time":1.445853625},
{"learn":[0.03947618531],"iteration":362,"passed_time":0.8366125924,"remaining_time":1.468105293},
{"learn":[0.03933299072],"iteration":363,"passed_time":0.85274756,"remaining_time":1.489965517},
{"learn":[0.03919062576],"iteration":364,"passed_time":0.8542907253,"remaining_time":1.48623181},
{"learn":[0.03905619257],"iteration":365,"passed_time":0.8554497779,"remaining_time":1.481844697},
{"learn":[0.0389598986],"iteration":366,"passed_time":0.8566163617,"remaining_time":1.477488166},
{"learn":[0.0388402241],"iteration":367,"passed_time":0.8577738458,"remaining_time":1.473133344},
{"learn":[0.03875313348],"iteration":368,"passed_time":0.8589066621,"remaining_time":1.468753669},
{"learn":[0.03864087903],"iteration":369,"passed_time":0.8599362073,"remaining_time":1.464215704},
{"learn":[0.03854874091],"iteration":370,"passed_time":0.8610053424,"remaining_time":1.459763775},
{"learn":[0.03838108807],"iteration":371,"passed_time":0.8621402581,"remaining_time":1.455441081},
{"learn":[0.03829330351],"iteration":372,"passed_time":0.8632102752,"remaining_time":1.451026387},
{"learn":[0.03822194464],"iteration":373,"passed_time":0.8643007308,"remaining_time":1.44666379},
{"learn":[0.03809963397],"iteration":374,"passed_time":0.8654762535,"remaining_time":1.442460422},
{"learn":[0.03798086275],"iteration":375,"passed_time":0.8667732263,"remaining_time":1.438474716},
{"learn":[0.03785500875],"iteration":376,"passed_time":0.8680953716,"remaining_time":1.434544871},
{"learn":[0.03777114744],"iteration":377,"passed_time":0.8693686187,"remaining_time":1.430548362},
{"learn":[0.03767907523],"iteration":378,"passed_time":0.871028965,"remaining_time":1.427200494},
{"learn":[0.03755817181],"iteration":379,"passed_time":0.8725629157,"remaining_time":1.423655284},
{"learn":[0.03747139132],"iteration":380,"passed_time":0.8737544727,"remaining_time":1.419564353},
{"learn":[0.03739586109],"iteration":381,"passed_time":0.8749161409,"remaining_time":1.415440249},
{"learn":[0.03730100151],"iteration":382,"passed_time":0.8759705345,"remaining_time":1.411158798},
{"learn":[0.0372076965],"iteration":383,"passed_time":0.8769739837,"remaining_time":1.406812432},
{"learn":[0.03707004563],"iteration":384,"passed_time":0.877982103,"remaining_time":1.402490892},
{"learn":[0.03696703717],"iteration":385,"passed_time":0.8789718229,"remaining_time":1.398157252},
{"learn":[0.03684644389],"iteration":386,"passed_time":0.8802160127,"remaining_time":1.394243968},
{"learn":[0.03678045816],"iteration":387,"passed_time":0.8814252928,"remaining_time":1.390289379},
{"learn":[0.03662245448],"iteration":388,"passed_time":0.8825979345,"remaining_time":1.386291357},
{"learn":[0.03652553636],"iteration":389,"passed_time":0.8837320737,"remaining_time":1.382247602},
{"learn":[0.03643560022],"iteration":390,"passed_time":0.8848863409,"remaining_time":1.378250081},
{"learn":[0.03633506124],"iteration":391,"passed_time":0.8861018796,"remaining_time":1.374362099},
{"learn":[0.03621401438],"iteration":392,"passed_time":0.8872887618,"remaining_time":1.370443456},
{"learn":[0.03613273109],"iteration":393,"passed_time":0.8883691959,"remaining_time":1.366374956},
{"learn":[0.03606258951],"iteration":394,"passed_time":0.8895577216,"remaining_time":1.362487143},
{"learn":[0.03594064325],"iteration":395,"passed_time":0.8907818636,"remaining_time":1.358667287},
{"learn":[0.0358640004],"iteration":396,"passed_time":0.8918742734,"remaining_time":1.35466042},
{"learn":[0.03567937138],"iteration":397,"passed_time":0.8929124371,"remaining_time":1.350586149},
{"learn":[0.0356576307],"iteration":398,"passed_time":0.8934528847,"remaining_time":1.345777403},
{"learn":[0.03557582406],"iteration":399,"passed_time":0.8944756201,"remaining_time":1.34171343},
{"learn":[0.03550600424],"iteration":400,"passed_time":0.8955195761,"remaining_time":1.337696324},
{"learn":[0.03538838828],"iteration":401,"passed_time":0.8966541463,"remaining_time":1.333828805},
{"learn":[0.03526433697],"iteration":402,"passed_time":0.8978878587,"remaining_time":1.330121716},
{"learn":[0.03520846948],"iteration":403,"passed_time":0.898954794,"remaining_time":1.326180835},
{"learn":[0.03504399555],"iteration":404,"passed_time":0.9001078389,"remaining_time":1.322380652},
{"learn":[0.0349699191],"iteration":405,"passed_time":0.9011725794,"remaining_time":1.318464316},
{"learn":[0.0348864222],"iteration":406,"passed_time":0.9022466849,"remaining_time":1.314575637},
{"learn":[0.03479492374],"iteration":407,"passed_time":0.9036354446,"remaining_time":1.311157312},
{"learn":[0.03471562921],"iteration":408,"passed_time":0.9046630557,"remaining_time":1.307227056},
{"learn":[0.03462133175],"iteration":409,"passed_time":0.9058083788,"remaining_time":1.30348035},
{"learn":[0.03457207408],"iteration":410,"passed_time":0.9068090922,"remaining_time":1.299539064},
{"learn":[0.03453167086],"iteration":411,"passed_time":0.9078030211,"remaining_time":1.29560237},
{"learn":[0.03446948819],"iteration":412,"passed_time":0.9089200437,"remaining_time":1.29185488},
{"learn":[0.03440951913],"iteration":413,"passed_time":0.9099749331,"remaining_time":1.288032152},
{"learn":[0.03434288211],"iteration":414,"passed_time":0.9110749392,"remaining_time":1.28428636},
{"learn":[0.03423943558],"iteration":415,"passed_time":0.912192448,"remaining_time":1.28057786},
{"learn":[0.0342033394],"iteration":416,"passed_time":0.9134396493,"remaining_time":1.277063107},
{"learn":[0.03411629917],"iteration":417,"passed_time":0.9146634755,"remaining_time":1.273526657},
{"learn":[0.0340120269],"iteration":418,"passed_time":0.9157675202,"remaining_time":1.269835153},
{"learn":[0.0339035135],"iteration":419,"passed_time":0.916909321,"remaining_time":1.26620811},
{"learn":[0.03383888462],"iteration":420,"passed_time":0.9180112913,"remaining_time":1.262538094},
{"learn":[0.03376327298],"iteration":421,"passed_time":0.9192517731,"remaining_time":1.259069964},
{"learn":[0.03365332906],"iteration":422,"passed_time":0.9204250313,"remaining_time":1.255520669},
{"learn":[0.03359126269],"iteration":423,"passed_time":0.921589736,"remaining_time":1.251970962},
{"learn":[0.03352749832],"iteration":424,"passed_time":0.9227061521,"remaining_time":1.248367147},
{"learn":[0.03346361377],"iteration":425,"passed_time":0.923869133,"remaining_time":1.244837752},
{"learn":[0.03337375517],"iteration":426,"passed_time":0.9250439828,"remaining_time":1.241335368},
{"learn":[0.03331587179],"iteration":427,"passed_time":0.9329873214,"remaining_time":1.246889598},
{"learn":[0.03317548395],"iteration":428,"passed_time":0.948579002,"remaining_time":1.262560863},
{"learn":[0.03312908343],"iteration":429,"passed_time":0.9632338912,"remaining_time":1.276844926},
{"learn":[0.03306683874],"iteration":430,"passed_time":0.979087077,"remaining_time":1.292576675},
{"learn":[0.03300086076],"iteration":431,"passed_time":0.9948638942,"remaining_time":1.308061787},
{"learn":[0.03289887963],"iteration":432,"passed_time":1.009167035,"remaining_time":1.321472769},
{"learn":[0.03273261466],"iteration":433,"passed_time":1.023586385,"remaining_time":1.334907589},
{"learn":[0.0326166812],"iteration":434,"passed_time":1.029114059,"remaining_time":1.336665387},
{"learn":[0.03256715604],"iteration":435,"passed_time":1.030491881,"remaining_time":1.333021607},
{"learn":[0.03245030186],"iteration":436,"passed_time":1.031752952,"remaining_time":1.329237785},
{"learn":[0.03238693873],"iteration":437,"passed_time":1.033032432,"remaining_time":1.325489103},
{"learn":[0.03233319569],"iteration":438,"passed_time":1.034283961,"remaining_time":1.32171595},
{"learn":[0.03225196086],"iteration":439,"passed_time":1.035439478,"remaining_time":1.317832063},
{"learn":[0.03216118541],"iteration":440,"passed_time":1.036545011,"remaining_time":1.31389719},
{"learn":[0.03205432349],"iteration":441,"passed_time":1.037699449,"remaining_time":1.31003686},
{"learn":[0.03192691687],"iteration":442,"passed_time":1.038799042,"remaining_time":1.306119789},
{"learn":[0.03186237134],"iteration":443,"passed_time":1.040620313,"remaining_time":1.303119131},
{"learn":[0.03181216193],"iteration":444,"passed_time":1.041712262,"remaining_time":1.299214169},
{"learn":[0.03174773658],"iteration":445,"passed_time":1.042728418,"remaining_time":1.295227676},
{"learn":[0.03167203578],"iteration":446,"passed_time":1.043758515,"remaining_time":1.291271719},
{"learn":[0.03159625356],"iteration":447,"passed_time":1.044840773,"remaining_time":1.287393095},
{"learn":[0.03148748817],"iteration":448,"passed_time":1.045920701,"remaining_time":1.283524067},
{"learn":[0.03142268096],"iteration":449,"passed_time":1.046936807,"remaining_time":1.279589431},
{"learn":[0.03136979274],"iteration":450,"passed_time":1.047943684,"remaining_time":1.275656502},
{"learn":[0.03131516581],"iteration":451,"passed_time":1.04867481,"remaining_time":1.271402203},
{"learn":[0.03125546424],"iteration":452,"passed_time":1.049732986,"remaining_time":1.267558374},
{"learn":[0.03119247716],"iteration":453,"passed_time":1.050779678,"remaining_time":1.263713005},
{"learn":[0.03107962376],"iteration":454,"passed_time":1.051825678,"remaining_time":1.259879109},
{"learn":[0.03095301574],"iteration":455,"passed_time":1.052844651,"remaining_time":1.256025198},
{"learn":[0.03090490171],"iteration":456,"passed_time":1.053999154,"remaining_time":1.252344728},
{"learn":[0.03080376765],"iteration":457,"passed_time":1.055020281,"remaining_time":1.24851745},
{"learn":[0.03077417079],"iteration":458,"passed_time":1.056069198,"remaining_time":1.244735154},
{"learn":[0.03064207721],"iteration":459,"passed_time":1.057159874,"remaining_time":1.241013765},
{"learn":[0.03054161382],"iteration":460,"passed_time":1.058256658,"remaining_time":1.23731093},
{"learn":[0.03044169899],"iteration":461,"passed_time":1.059717718,"remaining_time":1.234043576},
{"learn":[0.03037096427],"iteration":462,"passed_time":1.060906724,"remaining_time":1.23046849},
{"learn":[0.03027967709],"iteration":463,"passed_time":1.062248498,"remaining_time":1.227080162},
{"learn":[0.03016653294],"iteration":464,"passed_time":1.06342127,"remaining_time":1.223506193},
{"learn":[0.03007455958],"iteration":465,"passed_time":1.064505072,"remaining_time":1.219840576},
{"learn":[0.0300255946],"iteration":466,"passed_time":1.065610429,"remaining_time":1.216210618},
{"learn":[0.02994395853],"iteration":467,"passed_time":1.066682064,"remaining_time":1.212553116},
{"learn":[0.0298707524],"iteration":468,"passed_time":1.068022871,"remaining_time":1.209211396},
{"learn":[0.02979845535],"iteration":469,"passed_time":1.069335879,"remaining_time":1.205846842},
{"learn":[0.02972317711],"iteration":470,"passed_time":1.070532171,"remaining_time":1.202359912},
{"learn":[0.02965645674],"iteration":471,"passed_time":1.071757876,"remaining_time":1.19891559},
{"learn":[0.0296047548],"iteration":472,"passed_time":1.072966244,"remaining_time":1.195461334},
{"learn":[0.02951744514],"iteration":473,"passed_time":1.074230813,"remaining_time":1.192078919},
{"learn":[0.02945250224],"iteration":474,"passed_time":1.075343581,"remaining_time":1.188537642},
{"learn":[0.02936700495],"iteration":475,"passed_time":1.076658438,"remaining_time":1.185229036},
{"learn":[0.02928706301],"iteration":476,"passed_time":1.077854635,"remaining_time":1.181798688},
{"learn":[0.02923775882],"iteration":477,"passed_time":1.07895215,"remaining_time":1.178269922},
{"learn":[0.02914164124],"iteration":478,"passed_time":1.080138101,"remaining_time":1.174847496},
{"learn":[0.0290818292],"iteration":479,"passed_time":1.081218364,"remaining_time":1.171319895},
{"learn":[0.02901251917],"iteration":480,"passed_time":1.082301849,"remaining_time":1.167805945},
{"learn":[0.02897709947],"iteration":481,"passed_time":1.083484694,"remaining_time":1.164408862},
{"learn":[0.02884574053],"iteration":482,"passed_time":1.084885269,"remaining_time":1.161254004},
{"learn":[0.02878655651],"iteration":483,"passed_time":1.086077452,"remaining_time":1.157884226},
{"learn":[0.02872090805],"iteration":484,"passed_time":1.087302125,"remaining_time":1.154557927},
{"learn":[0.0286560078],"iteration":485,"passed_time":1.088485169,"remaining_time":1.151196249},
{"learn":[0.02857687997],"iteration":486,"passed_time":1.089652272,"remaining_time":1.147826726},
{"learn":[0.0285207353],"iteration":487,"passed_time":1.091087663,"remaining_time":1.144747712},
{"learn":[0.02847220646],"iteration":488,"passed_time":1.092362499,"remaining_time":1.141507642},
{"learn":[0.02839950236],"iteration":489,"passed_time":1.093571078,"remaining_time":1.138206632},
{"learn":[0.02830926771],"iteration":490,"passed_time":1.094827719,"remaining_time":1.13496397},
{"learn":[0.02822107222],"iteration":491,"passed_time":1.096130545,"remaining_time":1.131777067},
{"learn":[0.02815811033],"iteration":492,"passed_time":1.097197636,"remaining_time":1.128355378},
{"learn":[0.02810288251],"iteration":493,"passed_time":1.098358367,"remaining_time":1.125039137},
{"learn":[0.02803240753],"iteration":494,"passed_time":1.099594434,"remaining_time":1.121808463},
{"learn":[0.02795799573],"iteration":495,"passed_time":1.100796915,"remaining_time":1.118551704},
{"learn":[0.02790965685],"iteration":496,"passed_time":1.101965162,"remaining_time":1.115268564},
{"learn":[0.02785545054],"iteration":497,"passed_time":1.103234075,"remaining_time":1.112095393},
{"learn":[0.02782362651],"iteration":498,"passed_time":1.104761837,"remaining_time":1.10918974},
{"learn":[0.02777203893],"iteration":499,"passed_time":1.105890815,"remaining_time":1.105890815},
{"learn":[0.02773626258],"iteration":500,"passed_time":1.106909958,"remaining_time":1.102491156},
{"learn":[0.02767730728],"iteration":501,"passed_time":1.107931306,"remaining_time":1.099103168},
{"learn":[0.02762086023],"iteration":502,"passed_time":1.109290345,"remaining_time":1.096058253},
{"learn":[0.027536619],"iteration":503,"passed_time":1.110302693,"remaining_time":1.092678841},
{"learn":[0.02747937334],"iteration":504,"passed_time":1.111330146,"remaining_time":1.089323608},
{"learn":[0.0274043529],"iteration":505,"passed_time":1.112500563,"remaining_time":1.08611715},
{"learn":[0.02734506033],"iteration":506,"passed_time":1.113578792,"remaining_time":1.082829082},
{"learn":[0.0272735774],"iteration":507,"passed_time":1.114649606,"remaining_time":1.079542532},
{"learn":[0.02722294931],"iteration":508,"passed_time":1.115756006,"remaining_time":1.076299015},
{"learn":[0.02718774671],"iteration":509,"passed_time":1.116789029,"remaining_time":1.07299338},
{"learn":[0.02711802769],"iteration":510,"passed_time":1.117793961,"remaining_time":1.069669759},
{"learn":[0.02705737246],"iteration":511,"passed_time":1.118802531,"remaining_time":1.066358663},
{"learn":[0.02697346075],"iteration":512,"passed_time":1.119869066,"remaining_time":1.063111569},
{"learn":[0.02690706602],"iteration":513,"passed_time":1.120908041,"remaining_time":1.059846903},
{"learn":[0.02685876009],"iteration":514,"passed_time":1.121941725,"remaining_time":1.056585896},
{"learn":[0.02677586408],"iteration":515,"passed_time":1.122949253,"remaining_time":1.053308989},
{"learn":[0.02669077966],"iteration":516,"passed_time":1.124005606,"remaining_time":1.050086475},
{"learn":[0.02663965923],"iteration":517,"passed_time":1.124820391,"remaining_time":1.046647545},
{"learn":[0.02658968825],"iteration":518,"passed_time":1.125827047,"remaining_time":1.04339655},
{"learn":[0.02654814526],"iteration":519,"passed_time":1.126836479,"remaining_time":1.04015675},
{"learn":[0.02648498372],"iteration":520,"passed_time":1.127855802,"remaining_time":1.036934605},
{"learn":[0.02644191525],"iteration":521,"passed_time":1.12887232,"remaining_time":1.033718331},
{"learn":[0.0263871003],"iteration":522,"passed_time":1.129880118,"remaining_time":1.030502517},
{"learn":[0.02632673],"iteration":523,"passed_time":1.130939808,"remaining_time":1.027342268},
{"learn":[0.02629903468],"iteration":524,"passed_time":1.131995489,"remaining_time":1.024186395},
{"learn":[0.02627298309],"iteration":525,"passed_time":1.133052042,"remaining_time":1.021039293},
{"learn":[0.02619757303],"iteration":526,"passed_time":1.134102983,"remaining_time":1.017895087},
{"learn":[0.02614299456],"iteration":527,"passed_time":1.135140706,"remaining_time":1.014746995},
{"learn":[0.02606705921],"iteration":528,"passed_time":1.136212221,"remaining_time":1.011636968},
{"learn":[0.02598201744],"iteration":529,"passed_time":1.137263032,"remaining_time":1.008516273},
{"learn":[0.02593486871],"iteration":530,"passed_time":1.138305364,"remaining_time":1.005395887},
{"learn":[0.0258130562],"iteration":531,"passed_time":1.139317201,"remaining_time":1.002256485},
{"learn":[0.02573733989],"iteration":532,"passed_time":1.140322535,"remaining_time":0.9991193691},
{"learn":[0.02563087533],"iteration":533,"passed_time":1.141324882,"remaining_time":0.9959876308},
{"learn":[0.02558006116],"iteration":534,"passed_time":1.142366352,"remaining_time":0.9928978577},
{"learn":[0.02553484692],"iteration":535,"passed_time":1.143393322,"remaining_time":0.9898031743},
{"learn":[0.02542678709],"iteration":536,"passed_time":1.144417446,"remaining_time":0.9867137381},
{"learn":[0.02539075293],"iteration":537,"passed_time":1.145453886,"remaining_time":0.983642556},
{"learn":[0.02533950651],"iteration":538,"passed_time":1.146545844,"remaining_time":0.9806264087},
{"learn":[0.02529999299],"iteration":539,"passed_time":1.147637783,"remaining_time":0.9776173709},
{"learn":[0.0252288609],"iteration":540,"passed_time":1.148676318,"remaining_time":0.9745701106},
{"learn":[0.02516786839],"iteration":541,"passed_time":1.149705222,"remaining_time":0.9715221244},
{"learn":[0.02511452659],"iteration":542,"passed_time":1.150736561,"remaining_time":0.9684836246},
{"learn":[0.02502987637],"iteration":543,"passed_time":1.151905544,"remaining_time":0.9655678828},
{"learn":[0.02496724012],"iteration":544,"passed_time":1.153226674,"remaining_time":0.9627855719},
{"learn":[0.02491997509],"iteration":545,"passed_time":1.15429379,"remaining_time":0.9597974002},
{"learn":[0.02486589091],"iteration":546,"passed_time":1.155345873,"remaining_time":0.9568038036},
{"learn":[0.02477647619],"iteration":547,"passed_time":1.15640436,"remaining_time":0.9538225746},
{"learn":[0.0247288545],"iteration":548,"passed_time":1.157458358,"remaining_time":0.950844662},
{"learn":[0.02465906376],"iteration":549,"passed_time":1.158504358,"remaining_time":0.9478672023},
{"learn":[0.02463071715],"iteration":550,"passed_time":1.159524854,"remaining_time":0.94487597},
{"learn":[0.02454425843],"iteration":551,"passed_time":1.160558709,"remaining_time":0.94190272},
{"learn":[0.02449233164],"iteration":552,"passed_time":1.162149195,"remaining_time":0.93938642},
{"learn":[0.02444251378],"iteration":553,"passed_time":1.163323776,"remaining_time":0.9365386354},
{"learn":[0.02434397131],"iteration":554,"passed_time":1.164564188,"remaining_time":0.9337496641},
{"learn":[0.02429646787],"iteration":555,"passed_time":1.165681301,"remaining_time":0.9308678012},
{"learn":[0.02423769866],"iteration":556,"passed_time":1.166919593,"remaining_time":0.9280886528},
{"learn":[0.02420488218],"iteration":557,"passed_time":1.168141535,"remaining_time":0.9253020761},
{"learn":[0.02415762878],"iteration":558,"passed_time":1.169241306,"remaining_time":0.9224247152},
{"learn":[0.02409836335],"iteration":559,"passed_time":1.170346583,"remaining_time":0.9195580296},
{"learn":[0.02407282349],"iteration":560,"passed_time":1.171492618,"remaining_time":0.9167295173},
{"learn":[0.02399343785],"iteration":561,"passed_time":1.172558972,"remaining_time":0.9138448926},
{"learn":[0.02394496135],"iteration":562,"passed_time":1.17362746,"remaining_time":0.910968384},
{"learn":[0.02388148579],"iteration":563,"passed_time":1.174695678,"remaining_time":0.9080980776},
{"learn":[0.02383506201],"iteration":564,"passed_time":1.176159363,"remaining_time":0.905538625},
{"learn":[0.02378381559],"iteration":565,"passed_time":1.177304035,"remaining_time":0.9027384298},
{"learn":[0.02372130727],"iteration":566,"passed_time":1.17851795,"remaining_time":0.8999969531},
{"learn":[0.02367596898],"iteration":567,"passed_time":1.179667636,"remaining_time":0.8972120048},
{"learn":[0.023613513],"iteration":568,"passed_time":1.180805403,"remaining_time":0.8944237762},
{"learn":[0.02355511596],"iteration":569,"passed_time":1.182024043,"remaining_time":0.8917023484},
{"learn":[0.02352917097],"iteration":570,"passed_time":1.183017311,"remaining_time":0.8888168586},
{"learn":[0.02347917479],"iteration":571,"passed_time":1.184226422,"remaining_time":0.8860994908},
{"learn":[0.02343972718],"iteration":572,"passed_time":1.185364839,"remaining_time":0.8833347054},
{"learn":[0.02338240786],"iteration":573,"passed_time":1.186502355,"remaining_time":0.8805749187},
{"learn":[0.02335104128],"iteration":574,"passed_time":1.187579763,"remaining_time":0.8777763465},
{"learn":[0.02329097918],"iteration":575,"passed_time":1.188632304,"remaining_time":0.874965446},
{"learn":[0.02324564476],"iteration":576,"passed_time":1.189725335,"remaining_time":0.8721903237},
{"learn":[0.02320787771],"iteration":577,"passed_time":1.190776712,"remaining_time":0.86939061},
{"learn":[0.02315331281],"iteration":578,"passed_time":1.19182837,"remaining_time":0.8665971395},
{"learn":[0.02311132206],"iteration":579,"passed_time":1.192984281,"remaining_time":0.8638851688},
{"learn":[0.02305501457],"iteration":580,"passed_time":1.194189763,"remaining_time":0.8612143039},
{"learn":[0.02299955027],"iteration":581,"passed_time":1.195377971,"remaining_time":0.8585360685},
{"learn":[0.02295931374],"iteration":582,"passed_time":1.196388566,"remaining_time":0.8557359037},
{"learn":[0.0229098099],"iteration":583,"passed_time":1.197446578,"remaining_time":0.8529756449},
{"learn":[0.02285160282],"iteration":584,"passed_time":1.19893681,"remaining_time":0.8505278227},
{"learn":[0.02277801095],"iteration":585,"passed_time":1.200130602,"remaining_time":0.8478738386},
{"learn":[0.02273246331],"iteration":586,"passed_time":1.201253402,"remaining_time":0.845174881},
{"learn":[0.02268203875],"iteration":587,"passed_time":1.213937069,"remaining_time":0.850581756},
{"learn":[0.02262137964],"iteration":588,"passed_time":1.228481856,"remaining_time":0.8572258792},
{"learn":[0.02256818709],"iteration":589,"passed_time":1.246931315,"remaining_time":0.8665115915},
{"learn":[0.02253003237],"iteration":590,"passed_time":1.262357195,"remaining_time":0.8736109862},
{"learn":[0.02248286813],"iteration":591,"passed_time":1.278247576,"remaining_time":0.8809544102},
{"learn":[0.02241980933],"iteration":592,"passed_time":1.296138411,"remaining_time":0.8895924674},
{"learn":[0.02237395155],"iteration":593,"passed_time":1.311194334,"remaining_time":0.8962035347},
{"learn":[0.02230265664],"iteration":594,"passed_time":1.321077371,"remaining_time":0.8992207313},
{"learn":[0.02226978395],"iteration":595,"passed_time":1.32242796,"remaining_time":0.8964108992},
{"learn":[0.02221678137],"iteration":596,"passed_time":1.323620895,"remaining_time":0.8934995323},
{"learn":[0.02217881272],"iteration":597,"passed_time":1.32488766,"remaining_time":0.8906435441},
{"learn":[0.0221441645],"iteration":598,"passed_time":1.326713524,"remaining_time":0.8881671506},
{"learn":[0.02208160773],"iteration":599,"passed_time":1.328250216,"remaining_time":0.885500144},
{"learn":[0.0220544125],"iteration":600,"passed_time":1.329509473,"remaining_time":0.8826527118},
{"learn":[0.02199601546],"iteration":601,"passed_time":1.330771301,"remaining_time":0.8798122553},
{"learn":[0.02195942499],"iteration":602,"passed_time":1.331858459,"remaining_time":0.876862037},
{"learn":[0.02190017894],"iteration":603,"passed_time":1.333178667,"remaining_time":0.8740707817},
{"learn":[0.02186622658],"iteration":604,"passed_time":1.334207305,"remaining_time":0.8710940258},
{"learn":[0.02181136705],"iteration":605,"passed_time":1.33537677,"remaining_time":0.8682152599},
{"learn":[0.02178548022],"iteration":606,"passed_time":1.336519418,"remaining_time":0.865324763},
{"learn":[0.02174445866],"iteration":607,"passed_time":1.337794549,"remaining_time":0.8625254328},
{"learn":[0.02171847685],"iteration":608,"passed_time":1.338978961,"remaining_time":0.8596728631},
{"learn":[0.02168646091],"iteration":609,"passed_time":1.340079112,"remaining_time":0.8567718914},
{"learn":[0.02163827129],"iteration":610,"passed_time":1.341116444,"remaining_time":0.8538368195},
{"learn":[0.0215692714],"iteration":611,"passed_time":1.342114281,"remaining_time":0.8508829104},
{"learn":[0.02153170787],"iteration":612,"passed_time":1.343153362,"remaining_time":0.8479614209},
{"learn":[0.02148828274],"iteration":613,"passed_time":1.34421534,"remaining_time":0.8450604579},
{"learn":[0.02146449709],"iteration":614,"passed_time":1.345252662,"remaining_time":0.8421500402},
{"learn":[0.02143884093],"iteration":615,"passed_time":1.346350259,"remaining_time":0.8392832784},
{"learn":[0.02140182014],"iteration":616,"passed_time":1.347359491,"remaining_time":0.8363673987},
{"learn":[0.02136199843],"iteration":617,"passed_time":1.348606853,"remaining_time":0.833604883},
{"learn":[0.02133861015],"iteration":618,"passed_time":1.349665477,"remaining_time":0.8307310931},
{"learn":[0.02131145756],"iteration":619,"passed_time":1.350797066,"remaining_time":0.8279078789},
{"learn":[0.02127202352],"iteration":620,"passed_time":1.351898755,"remaining_time":0.8250718651},
{"learn":[0.0212352993],"iteration":621,"passed_time":1.35299108,"remaining_time":0.8222357366},
{"learn":[0.02117747408],"iteration":622,"passed_time":1.354005342,"remaining_time":0.8193579679},
{"learn":[0.02116377373],"iteration":623,"passed_time":1.354623616,"remaining_time":0.8162475638},
{"learn":[0.02111381438],"iteration":624,"passed_time":1.355832361,"remaining_time":0.8134994164},
{"learn":[0.02105907115],"iteration":625,"passed_time":1.357060351,"remaining_time":0.8107676857},
{"learn":[0.02100985225],"iteration":626,"passed_time":1.358178997,"remaining_time":0.8079757031},
{"learn":[0.02096164905],"iteration":627,"passed_time":1.359204929,"remaining_time":0.80513413},
{"learn":[0.02092176724],"iteration":628,"passed_time":1.360261091,"remaining_time":0.8023161604},
{"learn":[0.02089434523],"iteration":629,"passed_time":1.361292997,"remaining_time":0.7994895378},
{"learn":[0.02084577956],"iteration":630,"passed_time":1.362291796,"remaining_time":0.7966492437},
{"learn":[0.02080656455],"iteration":631,"passed_time":1.363282799,"remaining_time":0.7938102372},
{"learn":[0.02072245319],"iteration":632,"passed_time":1.364402622,"remaining_time":0.7910517572},
{"learn":[0.02068739015],"iteration":633,"passed_time":1.365558062,"remaining_time":0.7883190074},
{"learn":[0.0206350156],"iteration":634,"passed_time":1.366699036,"remaining_time":0.7855829104},
{"learn":[0.02059684342],"iteration":635,"passed_time":1.367909884,"remaining_time":0.7828918206},
{"learn":[0.02056324773],"iteration":636,"passed_time":1.369027764,"remaining_time":0.7801523991},
{"learn":[0.02051027228],"iteration":637,"passed_time":1.370306367,"remaining_time":0.7775092554},
{"learn":[0.02047829318],"iteration":638,"passed_time":1.371480026,"remaining_time":0.7748110947},
{"learn":[0.02042840361],"iteration":639,"passed_time":1.372568964,"remaining_time":0.772070042},
{"learn":[0.02036789568],"iteration":640,"passed_time":1.373634095,"remaining_time":0.7693208113},
{"learn":[0.02033508115],"iteration":641,"passed_time":1.374697728,"remaining_time":0.7665759918},
{"learn":[0.02026941912],"iteration":642,"passed_time":1.375807626,"remaining_time":0.7638620876},
{"learn":[0.02021946752],"iteration":643,"passed_time":1.376970777,"remaining_time":0.7611826034},
{"learn":[0.02017603463],"iteration":644,"passed_time":1.378137616,"remaining_time":0.7585098507},
{"learn":[0.02013741858],"iteration":645,"passed_time":1.37938142,"remaining_time":0.7558839362},
{"learn":[0.02011832958],"iteration":646,"passed_time":1.380302683,"remaining_time":0.7530863173},
{"learn":[0.02008703084],"iteration":647,"passed_time":1.38147762,"remaining_time":0.7504322874},
{"learn":[0.02005374141],"iteration":648,"passed_time":1.382576293,"remaining_time":0.74774157},
{"learn":[0.02001343704],"iteration":649,"passed_time":1.383693471,"remaining_time":0.7450657152},
{"learn":[0.01998723038],"iteration":650,"passed_time":1.384793452,"remaining_time":0.7423854298},
{"learn":[0.01996323733],"iteration":651,"passed_time":1.38604364,"remaining_time":0.7397901637},
{"learn":[0.0199385736],"iteration":652,"passed_time":1.387258111,"remaining_time":0.7371800377},
{"learn":[0.01990919772],"iteration":653,"passed_time":1.388338626,"remaining_time":0.7345033096},
{"learn":[0.01986134149],"iteration":654,"passed_time":1.389443587,"remaining_time":0.7318443322},
{"learn":[0.01983169618],"iteration":655,"passed_time":1.390514185,"remaining_time":0.7291720728},
{"learn":[0.0197851212],"iteration":656,"passed_time":1.391573209,"remaining_time":0.7264986462},
{"learn":[0.01975408221],"iteration":657,"passed_time":1.392572048,"remaining_time":0.7237988456},
{"learn":[0.0196977437],"iteration":658,"passed_time":1.393554733,"remaining_time":0.7210958481},
{"learn":[0.01967233952],"iteration":659,"passed_time":1.394170572,"remaining_time":0.7182090825},
{"learn":[0.01963492913],"iteration":660,"passed_time":1.395381611,"remaining_time":0.7156344419},
{"learn":[0.01959527023],"iteration":661,"passed_time":1.39654145,"remaining_time":0.7130377796},
{"learn":[0.01955022657],"iteration":662,"passed_time":1.397761403,"remaining_time":0.7104760073},
{"learn":[0.01950759035],"iteration":663,"passed_time":1.398775365,"remaining_time":0.70781404},
{"learn":[0.01948563258],"iteration":664,"passed_time":1.399825314,"remaining_time":0.705175158},
{"learn":[0.01945781708],"iteration":665,"passed_time":1.400854829,"remaining_time":0.7025308},
{"learn":[0.01941336849],"iteration":666,"passed_time":1.402079903,"remaining_time":0.699988917},
{"learn":[0.01937139325],"iteration":667,"passed_time":1.403143336,"remaining_time":0.6973706399},
{"learn":[0.01933426198],"iteration":668,"passed_time":1.404298961,"remaining_time":0.6948026249},
{"learn":[0.01928400024],"iteration":669,"passed_time":1.405427092,"remaining_time":0.6922252842},
{"learn":[0.01925086006],"iteration":670,"passed_time":1.406453571,"remaining_time":0.6896024214},
{"learn":[0.01921502555],"iteration":671,"passed_time":1.407455377,"remaining_time":0.6869722671},
{"learn":[0.01918988305],"iteration":672,"passed_time":1.408487562,"remaining_time":0.6843617131},
{"learn":[0.01915423851],"iteration":673,"passed_time":1.409509792,"remaining_time":0.681751027},
{"learn":[0.01911745226],"iteration":674,"passed_time":1.410583271,"remaining_time":0.6791697232},
{"learn":[0.01906221863],"iteration":675,"passed_time":1.41175217,"remaining_time":0.6766386139},
{"learn":[0.01901538779],"iteration":676,"passed_time":1.412856846,"remaining_time":0.6740808881},
{"learn":[0.01897420147],"iteration":677,"passed_time":1.413997484,"remaining_time":0.6715445279},
{"learn":[0.01893154005],"iteration":678,"passed_time":1.415024334,"remaining_time":0.6689584846},
{"learn":[0.01890242778],"iteration":679,"passed_time":1.416493746,"remaining_time":0.6665852921},
{"learn":[0.01885777566],"iteration":680,"passed_time":1.417666222,"remaining_time":0.6640756605},
{"learn":[0.01883765352],"iteration":681,"passed_time":1.418745784,"remaining_time":0.6615266267},
{"learn":[0.01879123556],"iteration":682,"passed_time":1.419781788,"remaining_time":0.6589616792},
{"learn":[0.01874658732],"iteration":683,"passed_time":1.420789467,"remaining_time":0.6563881162},
{"learn":[0.01871687804],"iteration":684,"passed_time":1.421811245,"remaining_time":0.6538256091},
{"learn":[0.01867420693],"iteration":685,"passed_time":1.422894526,"remaining_time":0.6512957449},
{"learn":[0.01865400919],"iteration":686,"passed_time":1.424006803,"remaining_time":0.6487833031},
{"learn":[0.0186093687],"iteration":687,"passed_time":1.425068271,"remaining_time":0.6462518905},
{"learn":[0.01856805639],"iteration":688,"passed_time":1.426076782,"remaining_time":0.6437008405},
{"learn":[0.01853931629],"iteration":689,"passed_time":1.427237623,"remaining_time":0.6412227001},
{"learn":[0.01852908173],"iteration":690,"passed_time":1.427900067,"remaining_time":0.6385255002},
{"learn":[0.01848804272],"iteration":691,"passed_time":1.42906885,"remaining_time":0.6360595461},
{"learn":[0.01844347202],"iteration":692,"passed_time":1.430131371,"remaining_time":0.633550261},
{"learn":[0.01840167317],"iteration":693,"passed_time":1.431192233,"remaining_time":0.6310444141},
{"learn":[0.01836157233],"iteration":694,"passed_time":1.432305949,"remaining_time":0.6285659199},
{"learn":[0.01833538117],"iteration":695,"passed_time":1.433733461,"remaining_time":0.6262284084},
{"learn":[0.01829166722],"iteration":696,"passed_time":1.434844291,"remaining_time":0.6237558394},
{"learn":[0.01825030257],"iteration":697,"passed_time":1.436035151,"remaining_time":0.621321799},
{"learn":[0.0182096396],"iteration":698,"passed_time":1.437197742,"remaining_time":0.6188791419},
{"learn":[0.01817892044],"iteration":699,"passed_time":1.438447188,"remaining_time":0.6164773662},
{"learn":[0.01815314215],"iteration":700,"passed_time":1.439616031,"remaining_time":0.6140444983},
{"learn":[0.01812618341],"iteration":701,"passed_time":1.440802547,"remaining_time":0.6116227338},
{"learn":[0.01809924599],"iteration":702,"passed_time":1.441937649,"remaining_time":0.609182762},
{"learn":[0.01807281835],"iteration":703,"passed_time":1.443204619,"remaining_time":0.6068019421},
{"learn":[0.018048143],"iteration":704,"passed_time":1.444457745,"remaining_time":0.604418489},
{"learn":[0.01801598557],"iteration":705,"passed_time":1.44553147,"remaining_time":0.6019635299},
{"learn":[0.01798222511],"iteration":706,"passed_time":1.446630975,"remaining_time":0.5995231621},
{"learn":[0.01795997077],"iteration":707,"passed_time":1.448152088,"remaining_time":0.5972604656},
{"learn":[0.01792223861],"iteration":708,"passed_time":1.449649204,"remaining_time":0.5949900119},
{"learn":[0.01788486892],"iteration":709,"passed_time":1.450724908,"remaining_time":0.5925496104},
{"learn":[0.01784714645],"iteration":710,"passed_time":1.451727456,"remaining_time":0.5900833118},
{"learn":[0.01782230827],"iteration":711,"passed_time":1.45274244,"remaining_time":0.5876261554},
{"learn":[0.01779313591],"iteration":712,"passed_time":1.460189601,"remaining_time":0.5877621534},
{"learn":[0.01775802636],"iteration":713,"passed_time":1.47285121,"remaining_time":0.5899656109},
{"learn":[0.01772198638],"iteration":714,"passed_time":1.485798161,"remaining_time":0.5922412252},
{"learn":[0.01768770063],"iteration":715,"passed_time":1.500979859,"remaining_time":0.5953607262},
{"learn":[0.01765105782],"iteration":716,"passed_time":1.515287987,"remaining_time":0.5980843798},
{"learn":[0.01763617314],"iteration":717,"passed_time":1.542830383,"remaining_time":0.6059584514},
{"learn":[0.01760536093],"iteration":718,"passed_time":1.558264902,"remaining_time":0.6090019994},
{"learn":[0.01757110037],"iteration":719,"passed_time":1.57924753,"remaining_time":0.6141518173},
{"learn":[0.01753612069],"iteration":720,"passed_time":1.59336815,"remaining_time":0.6165738056},
{"learn":[0.01749990238],"iteration":721,"passed_time":1.609337185,"remaining_time":0.6196616863},
{"learn":[0.01746986552],"iteration":722,"passed_time":1.61927667,"remaining_time":0.6203867739},
{"learn":[0.01742824306],"iteration":723,"passed_time":1.620686474,"remaining_time":0.6178307554},
{"learn":[0.01739796584],"iteration":724,"passed_time":1.621988233,"remaining_time":0.6152369158},
{"learn":[0.01737175143],"iteration":725,"passed_time":1.628584295,"remaining_time":0.6146447616},
{"learn":[0.01732919662],"iteration":726,"passed_time":1.629888499,"remaining_time":0.6120489137},
{"learn":[0.01728633749],"iteration":727,"passed_time":1.631190438,"remaining_time":0.609455768},
{"learn":[0.0172529395],"iteration":728,"passed_time":1.632903095,"remaining_time":0.6070188459},
{"learn":[0.01721842308],"iteration":729,"passed_time":1.634192767,"remaining_time":0.6044274618},
{"learn":[0.01718017532],"iteration":730,"passed_time":1.63537304,"remaining_time":0.6017993814},
{"learn":[0.01715258079],"iteration":731,"passed_time":1.636726228,"remaining_time":0.5992385644},
{"learn":[0.0171219062],"iteration":732,"passed_time":1.638260054,"remaining_time":0.5967468409},
{"learn":[0.01708593989],"iteration":733,"passed_time":1.639546354,"remaining_time":0.5941680247},
{"learn":[0.01705298773],"iteration":734,"passed_time":1.640719071,"remaining_time":0.5915517738},
{"learn":[0.01700629839],"iteration":735,"passed_time":1.642068601,"remaining_time":0.5890028679},
{"learn":[0.01698145828],"iteration":736,"passed_time":1.643680686,"remaining_time":0.5865509096},
{"learn":[0.01694740513],"iteration":737,"passed_time":1.644843598,"remaining_time":0.5839417653},
{"learn":[0.0169200432],"iteration":738,"passed_time":1.645959539,"remaining_time":0.5813199453},
{"learn":[0.01689436378],"iteration":739,"passed_time":1.647139528,"remaining_time":0.578724699},
{"learn":[0.01686084949],"iteration":740,"passed_time":1.648365298,"remaining_time":0.5761492743},
{"learn":[0.01684089792],"iteration":741,"passed_time":1.649581303,"remaining_time":0.5735740918},
{"learn":[0.01679371043],"iteration":742,"passed_time":1.6508102,"remaining_time":0.5710070275},
{"learn":[0.01675737001],"iteration":743,"passed_time":1.65203597,"remaining_time":0.5684424844},
{"learn":[0.01672758126],"iteration":744,"passed_time":1.653112501,"remaining_time":0.5658304535},
{"learn":[0.01668929085],"iteration":745,"passed_time":1.654346559,"remaining_time":0.5632761744},
{"learn":[0.01664985874],"iteration":746,"passed_time":1.655525284,"remaining_time":0.5607066893},
{"learn":[0.01662054294],"iteration":747,"passed_time":1.656724944,"remaining_time":0.5581479757},
{"learn":[0.01659592574],"iteration":748,"passed_time":1.657998421,"remaining_time":0.5556176285},
{"learn":[0.01656970358],"iteration":749,"passed_time":1.659145092,"remaining_time":0.5530483641},
{"learn":[0.0165472302],"iteration":750,"passed_time":1.660352834,"remaining_time":0.5505031368},
{"learn":[0.01652437303],"iteration":751,"passed_time":1.661472437,"remaining_time":0.5479323995},
{"learn":[0.01648858311],"iteration":752,"passed_time":1.662621103,"remaining_time":0.5453750496},
{"learn":[0.01645555341],"iteration":753,"passed_time":1.663893172,"remaining_time":0.5428616981},
{"learn":[0.01642971892],"iteration":754,"passed_time":1.665133669,"remaining_time":0.5403413893},
{"learn":[0.01639963941],"iteration":755,"passed_time":1.666218382,"remaining_time":0.5377741869},
{"learn":[0.01636888729],"iteration":756,"passed_time":1.667315247,"remaining_time":0.5352148018},
{"learn":[0.01634446586],"iteration":757,"passed_time":1.669286429,"remaining_time":0.5329384114},
{"learn":[0.0163042681],"iteration":758,"passed_time":1.670635629,"remaining_time":0.5304653314},
{"learn":[0.01627817387],"iteration":759,"passed_time":1.671847895,"remaining_time":0.527951967},
{"learn":[0.01624464116],"iteration":760,"passed_time":1.672921084,"remaining_time":0.5253983431},
{"learn":[0.01622919532],"iteration":761,"passed_time":1.674040051,"remaining_time":0.522862903},
{"learn":[0.01619489988],"iteration":762,"passed_time":1.675094058,"remaining_time":0.5203109985},
{"learn":[0.01616906441],"iteration":763,"passed_time":1.676151644,"remaining_time":0.5177641203},
{"learn":[0.01615172867],"iteration":764,"passed_time":1.677333172,"remaining_time":0.5152592099},
{"learn":[0.01612498993],"iteration":765,"passed_time":1.678559812,"remaining_time":0.5127715351},
{"learn":[0.01609755144],"iteration":766,"passed_time":1.679706533,"remaining_time":0.5102628711},
{"learn":[0.01606350992],"iteration":767,"passed_time":1.680749517,"remaining_time":0.5077264165},
{"learn":[0.01602311638],"iteration":768,"passed_time":1.681855115,"remaining_time":0.5052126547},
{"learn":[0.01600684383],"iteration":769,"passed_time":1.6828754,"remaining_time":0.5026770675},
{"learn":[0.01598010024],"iteration":770,"passed_time":1.684032694,"remaining_time":0.500186105},
{"learn":[0.01594548012],"iteration":771,"passed_time":1.686448513,"remaining_time":0.4980702863},
{"learn":[0.0158981395],"iteration":772,"passed_time":1.68758857,"remaining_time":0.4955790497},
{"learn":[0.01587103731],"iteration":773,"passed_time":1.688811915,"remaining_time":0.4931156239},
{"learn":[0.01585012335],"iteration":774,"passed_time":1.689826328,"remaining_time":0.4905947404},
{"learn":[0.01582131735],"iteration":775,"passed_time":1.690849054,"remaining_time":0.4880801393},
{"learn":[0.01578907753],"iteration":776,"passed_time":1.691866613,"remaining_time":0.4855678955},
{"learn":[0.01576001082],"iteration":777,"passed_time":1.692870273,"remaining_time":0.4830555278},
{"learn":[0.01573714977],"iteration":778,"passed_time":1.693984009,"remaining_time":0.4805782618},
{"learn":[0.0157117737],"iteration":779,"passed_time":1.695178497,"remaining_time":0.4781272684},
{"learn":[0.01566290371],"iteration":780,"passed_time":1.696318258,"remaining_time":0.4756641467},
{"learn":[0.01564493412],"iteration":781,"passed_time":1.69754442,"remaining_time":0.4732284955},
{"learn":[0.01560599823],"iteration":782,"passed_time":1.698623265,"remaining_time":0.4707551068},
{"learn":[0.01557878459],"iteration":783,"passed_time":1.699728778,"remaining_time":0.4682926226},
{"learn":[0.01554750136],"iteration":784,"passed_time":1.700835033,"remaining_time":0.4658337988},
{"learn":[0.01552365854],"iteration":785,"passed_time":1.701916875,"remaining_time":0.4633717701},
{"learn":[0.01550464417],"iteration":786,"passed_time":1.703053339,"remaining_time":0.4609280321},
{"learn":[0.01548026442],"iteration":787,"passed_time":1.704059424,"remaining_time":0.4584525355},
{"learn":[0.01544694397],"iteration":788,"passed_time":1.705116824,"remaining_time":0.4559944866},
{"learn":[0.01541831241],"iteration":789,"passed_time":1.706185879,"remaining_time":0.4535430817},
{"learn":[0.01539859055],"iteration":790,"passed_time":1.707317272,"remaining_time":0.4511116434},
{"learn":[0.01536532825],"iteration":791,"passed_time":1.708336626,"remaining_time":0.4486540633},
{"learn":[0.01532317565],"iteration":792,"passed_time":1.70939125,"remaining_time":0.4462093174},
{"learn":[0.01528594746],"iteration":793,"passed_time":1.7105655,"remaining_time":0.4437991095},
{"learn":[0.01525825795],"iteration":794,"passed_time":1.711596383,"remaining_time":0.4413550421},
{"learn":[0.01522353219],"iteration":795,"passed_time":1.712697977,"remaining_time":0.4389326474},
{"learn":[0.01519595898],"iteration":796,"passed_time":1.713723544,"remaining_time":0.4364942025},
{"learn":[0.01516888587],"iteration":797,"passed_time":1.714815636,"remaining_time":0.4340761385},
{"learn":[0.01513620508],"iteration":798,"passed_time":1.716365907,"remaining_time":0.4317766549},
{"learn":[0.01509938492],"iteration":799,"passed_time":1.717688416,"remaining_time":0.429422104},
{"learn":[0.01507260547],"iteration":800,"passed_time":1.718843776,"remaining_time":0.4270286035},
{"learn":[0.01504712182],"iteration":801,"passed_time":1.729987292,"remaining_time":0.4271040946},
{"learn":[0.01502814138],"iteration":802,"passed_time":1.746698695,"remaining_time":0.4285176125},
{"learn":[0.01499422585],"iteration":803,"passed_time":1.761742756,"remaining_time":0.4294795772},
{"learn":[0.01497029095],"iteration":804,"passed_time":1.776101941,"remaining_time":0.430235874},
{"learn":[0.01494861424],"iteration":805,"passed_time":1.791736317,"remaining_time":0.4312615948},
{"learn":[0.01491731648],"iteration":806,"passed_time":1.806272772,"remaining_time":0.4319834511},
{"learn":[0.01489870917],"iteration":807,"passed_time":1.82077991,"remaining_time":0.4326605726},
{"learn":[0.01486837573],"iteration":808,"passed_time":1.832821532,"remaining_time":0.4327180625},
{"learn":[0.01483336697],"iteration":809,"passed_time":1.83415146,"remaining_time":0.4302330586},
{"learn":[0.0148063239],"iteration":810,"passed_time":1.835335937,"remaining_time":0.4277170064},
{"learn":[0.01478969179],"iteration":811,"passed_time":1.836459339,"remaining_time":0.4251900932},
{"learn":[0.01475454734],"iteration":812,"passed_time":1.837526254,"remaining_time":0.4226536402},
{"learn":[0.01474137519],"iteration":813,"passed_time":1.838585242,"remaining_time":0.4201189865},
{"learn":[0.01471796268],"iteration":814,"passed_time":1.839623005,"remaining_time":0.4175831361},
{"learn":[0.01470050288],"iteration":815,"passed_time":1.840628438,"remaining_time":0.4150436675},
{"learn":[0.01467391921],"iteration":816,"passed_time":1.841640176,"remaining_time":0.4125093661},
{"learn":[0.01463407617],"iteration":817,"passed_time":1.842687749,"remaining_time":0.4099867608},
{"learn":[0.01461543688],"iteration":818,"passed_time":1.843743992,"remaining_time":0.4074696734},
{"learn":[0.01457979233],"iteration":819,"passed_time":1.844769929,"remaining_time":0.4049494966},
{"learn":[0.0145524149],"iteration":820,"passed_time":1.845853731,"remaining_time":0.4024455758},
{"learn":[0.01450833363],"iteration":821,"passed_time":1.846951151,"remaining_time":0.3999480595},
{"learn":[0.01446728105],"iteration":822,"passed_time":1.848170864,"remaining_time":0.3974802465},
{"learn":[0.0144464456],"iteration":823,"passed_time":1.849251699,"remaining_time":0.3949857997},
{"learn":[0.01442010131],"iteration":824,"passed_time":1.850308492,"remaining_time":0.3924896801},
{"learn":[0.01438060815],"iteration":825,"passed_time":1.851360295,"remaining_time":0.3899959943},
{"learn":[0.01435844685],"iteration":826,"passed_time":1.852409663,"remaining_time":0.3875052861},
{"learn":[0.01433326946],"iteration":827,"passed_time":1.853458619,"remaining_time":0.3850179741},
{"learn":[0.0142994838],"iteration":828,"passed_time":1.854516175,"remaining_time":0.3825359057},
{"learn":[0.01425968922],"iteration":829,"passed_time":1.855554338,"remaining_time":0.3800532982},
{"learn":[0.01423796793],"iteration":830,"passed_time":1.856605109,"remaining_time":0.3775767309},
{"learn":[0.01421236895],"iteration":831,"passed_time":1.857643864,"remaining_time":0.3751011648},
{"learn":[0.01419162944],"iteration":832,"passed_time":1.858679582,"remaining_time":0.3726284396},
{"learn":[0.01415899614],"iteration":833,"passed_time":1.859761149,"remaining_time":0.3701682862},
{"learn":[0.01412606627],"iteration":834,"passed_time":1.860771713,"remaining_time":0.3676974044},
{"learn":[0.01410673014],"iteration":835,"passed_time":1.861808684,"remaining_time":0.3652351964},
{"learn":[0.01408978206],"iteration":836,"passed_time":1.862836355,"remaining_time":0.362774583},
{"learn":[0.01406590338],"iteration":837,"passed_time":1.863861271,"remaining_time":0.3603168566},
{"learn":[0.01404770409],"iteration":838,"passed_time":1.864872837,"remaining_time":0.3578599843},
{"learn":[0.01402456586],"iteration":839,"passed_time":1.865907063,"remaining_time":0.3554108691},
{"learn":[0.01400556991],"iteration":840,"passed_time":1.866931757,"remaining_time":0.3529633168},
{"learn":[0.01397899496],"iteration":841,"passed_time":1.867945609,"remaining_time":0.3505171095},
{"learn":[0.01395603118],"iteration":842,"passed_time":1.868963399,"remaining_time":0.348075034},
{"learn":[0.01392157582],"iteration":843,"passed_time":1.870006664,"remaining_time":0.3456410421},
{"learn":[0.0139018617],"iteration":844,"passed_time":1.871042432,"remaining_time":0.3432089668},
{"learn":[0.01387465582],"iteration":845,"passed_time":1.87213417,"remaining_time":0.3407903809},
{"learn":[0.01385579264],"iteration":846,"passed_time":1.873278271,"remaining_time":0.3383843866},
{"learn":[0.01382675597],"iteration":847,"passed_time":1.874344946,"remaining_time":0.3359674903},
{"learn":[0.01381086237],"iteration":848,"passed_time":1.875413484,"remaining_time":0.3335541062},
{"learn":[0.01379389395],"iteration":849,"passed_time":1.876445926,"remaining_time":0.3311375163},
{"learn":[0.01377887551],"iteration":850,"passed_time":1.877469027,"remaining_time":0.3287225441},
{"learn":[0.01375946378],"iteration":851,"passed_time":1.878477447,"remaining_time":0.3263082889},
{"learn":[0.01373574889],"iteration":852,"passed_time":1.879488903,"remaining_time":0.3238978532},
{"learn":[0.0137124992],"iteration":853,"passed_time":1.880495449,"remaining_time":0.3214898543},
{"learn":[0.01369234023],"iteration":854,"passed_time":1.881521627,"remaining_time":0.3190884631},
{"learn":[0.01366422622],"iteration":855,"passed_time":1.882965074,"remaining_time":0.3167604797},
{"learn":[0.01364222581],"iteration":856,"passed_time":1.884178563,"remaining_time":0.3143961896},
{"learn":[0.01361903524],"iteration":857,"passed_time":1.8852859,"remaining_time":0.3120170138},
{"learn":[0.01357799526],"iteration":858,"passed_time":1.886331074,"remaining_time":0.3096305953},
{"learn":[0.01356574966],"iteration":859,"passed_time":1.887570964,"remaining_time":0.3072789942},
{"learn":[0.0135460462],"iteration":860,"passed_time":1.888840338,"remaining_time":0.3049347352},
{"learn":[0.01353080486],"iteration":861,"passed_time":1.890170417,"remaining_time":0.3026026886},
{"learn":[0.01350529019],"iteration":862,"passed_time":1.891635705,"remaining_time":0.3002944283},
{"learn":[0.01348510215],"iteration":863,"passed_time":1.892825519,"remaining_time":0.2979447576},
{"learn":[0.01346184955],"iteration":864,"passed_time":1.894090732,"remaining_time":0.2956095362},
{"learn":[0.01343900692],"iteration":865,"passed_time":1.895178223,"remaining_time":0.2932492863},
{"learn":[0.01341705206],"iteration":866,"passed_time":1.89641624,"remaining_time":0.2909150633},
{"learn":[0.01338563411],"iteration":867,"passed_time":1.897593381,"remaining_time":0.2885741086},
{"learn":[0.01336716927],"iteration":868,"passed_time":1.898741485,"remaining_time":0.2862314552},
{"learn":[0.0133339942],"iteration":869,"passed_time":1.899890171,"remaining_time":0.2838916347},
{"learn":[0.01331919577],"iteration":870,"passed_time":1.901023939,"remaining_time":0.28155234},
{"learn":[0.01329515814],"iteration":871,"passed_time":1.902169699,"remaining_time":0.2792175706},
{"learn":[0.01327311411],"iteration":872,"passed_time":1.90366915,"remaining_time":0.2769369782},
{"learn":[0.01325601872],"iteration":873,"passed_time":1.904890676,"remaining_time":0.2746181066},
{"learn":[0.01323000202],"iteration":874,"passed_time":1.905953508,"remaining_time":0.2722790725},
{"learn":[0.01320751702],"iteration":875,"passed_time":1.907080506,"remaining_time":0.2699520351},
{"learn":[0.01318865094],"iteration":876,"passed_time":1.908144671,"remaining_time":0.2676189219},
{"learn":[0.01316124637],"iteration":877,"passed_time":1.909154955,"remaining_time":0.2652812124},
{"learn":[0.01314653614],"iteration":878,"passed_time":1.910186544,"remaining_time":0.262949456},
{"learn":[0.01312222229],"iteration":879,"passed_time":1.91122107,"remaining_time":0.260621055},
{"learn":[0.01310186754],"iteration":880,"passed_time":1.91238813,"remaining_time":0.2583134931},
{"learn":[0.01308006872],"iteration":881,"passed_time":1.913681089,"remaining_time":0.2560253611},
{"learn":[0.01306598942],"iteration":882,"passed_time":1.914790781,"remaining_time":0.2537151997},
{"learn":[0.01304146332],"iteration":883,"passed_time":1.915870639,"remaining_time":0.2514038395},
{"learn":[0.01302735592],"iteration":884,"passed_time":1.917031275,"remaining_time":0.2491057589},
{"learn":[0.01300582459],"iteration":885,"passed_time":1.918049085,"remaining_time":0.2467918687},
{"learn":[0.01298593215],"iteration":886,"passed_time":1.919071946,"remaining_time":0.2444815444},
{"learn":[0.01296448029],"iteration":887,"passed_time":1.920366188,"remaining_time":0.242208348},
{"learn":[0.01295395595],"iteration":888,"passed_time":1.921369256,"remaining_time":0.2399009983},
{"learn":[0.01292753026],"iteration":889,"passed_time":1.922471137,"remaining_time":0.2376087922},
{"learn":[0.01290892392],"iteration":890,"passed_time":1.923506579,"remaining_time":0.2353111303},
{"learn":[0.01288451121],"iteration":891,"passed_time":1.924560346,"remaining_time":0.2330185173},
{"learn":[0.01287070329],"iteration":892,"passed_time":1.92557275,"remaining_time":0.2307237226},
{"learn":[0.01284621595],"iteration":893,"passed_time":1.926593566,"remaining_time":0.2284327942},
{"learn":[0.01282580112],"iteration":894,"passed_time":1.927606145,"remaining_time":0.2261437377},
{"learn":[0.01279449657],"iteration":895,"passed_time":1.928770519,"remaining_time":0.2238751495},
{"learn":[0.01277578652],"iteration":896,"passed_time":1.930046206,"remaining_time":0.2216218052},
{"learn":[0.01275880938],"iteration":897,"passed_time":1.931079229,"remaining_time":0.219343075},
{"learn":[0.0127479875],"iteration":898,"passed_time":1.932310782,"remaining_time":0.2170894205},
{"learn":[0.01272285469],"iteration":899,"passed_time":1.933368708,"remaining_time":0.2148187453},
{"learn":[0.01270309018],"iteration":900,"passed_time":1.934395217,"remaining_time":0.2125473102},
{"learn":[0.01267320935],"iteration":901,"passed_time":1.935607263,"remaining_time":0.2102987935},
{"learn":[0.01266242527],"iteration":902,"passed_time":1.936712725,"remaining_time":0.2080411233},
{"learn":[0.01263617694],"iteration":903,"passed_time":1.937737941,"remaining_time":0.2057774805},
{"learn":[0.01261259191],"iteration":904,"passed_time":1.938768328,"remaining_time":0.2035171173},
{"learn":[0.01259141434],"iteration":905,"passed_time":1.93986389,"remaining_time":0.2012662314},
{"learn":[0.01257218384],"iteration":906,"passed_time":1.940957622,"remaining_time":0.1990177055},
{"learn":[0.0125601563],"iteration":907,"passed_time":1.942039373,"remaining_time":0.1967705091},
{"learn":[0.01253469882],"iteration":908,"passed_time":1.94306039,"remaining_time":0.194519797},
{"learn":[0.01251704712],"iteration":909,"passed_time":1.94417339,"remaining_time":0.1922808847},
{"learn":[0.01249261406],"iteration":910,"passed_time":1.945320392,"remaining_time":0.190047766},
{"learn":[0.01246763245],"iteration":911,"passed_time":1.946569477,"remaining_time":0.1878268794},
{"learn":[0.01245070667],"iteration":912,"passed_time":1.947761921,"remaining_time":0.1856027242},
{"learn":[0.01242093924],"iteration":913,"passed_time":1.948901756,"remaining_time":0.1833758764},
{"learn":[0.01240538775],"iteration":914,"passed_time":1.950425171,"remaining_time":0.1811870377},
{"learn":[0.01238101285],"iteration":915,"passed_time":1.95168139,"remaining_time":0.1789751493},
{"learn":[0.01235544778],"iteration":916,"passed_time":1.952931083,"remaining_time":0.1767647545},
{"learn":[0.01233120081],"iteration":917,"passed_time":1.954079353,"remaining_time":0.1745473931},
{"learn":[0.01231311007],"iteration":918,"passed_time":1.955123935,"remaining_time":0.1723232195},
{"learn":[0.01228323118],"iteration":919,"passed_time":1.956165847,"remaining_time":0.170101378},
{"learn":[0.01226164655],"iteration":920,"passed_time":1.957176712,"remaining_time":0.1678794357},
{"learn":[0.01224574907],"iteration":921,"passed_time":1.958191045,"remaining_time":0.1656604137},
{"learn":[0.01222763217],"iteration":922,"passed_time":1.959245834,"remaining_time":0.1634473772},
{"learn":[0.01221215143],"iteration":923,"passed_time":1.960537505,"remaining_time":0.1612563316},
{"learn":[0.01218925065],"iteration":924,"passed_time":1.961642282,"remaining_time":0.1590520769},
{"learn":[0.01217134794],"iteration":925,"passed_time":1.962801334,"remaining_time":0.1568545343},
{"learn":[0.01215135954],"iteration":926,"passed_time":1.963872959,"remaining_time":0.1546523474},
{"learn":[0.01211838994],"iteration":927,"passed_time":1.964896842,"remaining_time":0.1524488929},
{"learn":[0.01208280936],"iteration":928,"passed_time":1.966058821,"remaining_time":0.1502585321},
{"learn":[0.01205742456],"iteration":929,"passed_time":1.967241224,"remaining_time":0.1480719201},
{"learn":[0.0120365484],"iteration":930,"passed_time":1.968291418,"remaining_time":0.1458776669},
{"learn":[0.01201910217],"iteration":931,"passed_time":1.969425167,"remaining_time":0.143691965},
{"learn":[0.0119937009],"iteration":932,"passed_time":1.970503206,"remaining_time":0.1415045175},
{"learn":[0.0119773101],"iteration":933,"passed_time":1.971538959,"remaining_time":0.1393164575},
{"learn":[0.01195599975],"iteration":934,"passed_time":1.972621784,"remaining_time":0.1371341347},
{"learn":[0.0119392552],"iteration":935,"passed_time":1.973704443,"remaining_time":0.1349541499},
{"learn":[0.01192296133],"iteration":936,"passed_time":1.974797604,"remaining_time":0.1327772135},
{"learn":[0.01189526504],"iteration":937,"passed_time":1.976054778,"remaining_time":0.1306134288},
{"learn":[0.01187976783],"iteration":938,"passed_time":1.977205428,"remaining_time":0.128444655},
{"learn":[0.01186859317],"iteration":939,"passed_time":1.978362812,"remaining_time":0.1262784773},
{"learn":[0.01184820547],"iteration":940,"passed_time":1.979600403,"remaining_time":0.1241194726},
{"learn":[0.01182946442],"iteration":941,"passed_time":1.980837392,"remaining_time":0.1219623872},
{"learn":[0.0118070269],"iteration":942,"passed_time":1.982085816,"remaining_time":0.1198079443},
{"learn":[0.01178483459],"iteration":943,"passed_time":1.983295878,"remaining_time":0.1176531453},
{"learn":[0.01176899042],"iteration":944,"passed_time":1.984320623,"remaining_time":0.1154895601},
{"learn":[0.0117527954],"iteration":945,"passed_time":1.985314602,"remaining_time":0.1133266263},
{"learn":[0.01173426175],"iteration":946,"passed_time":1.986367752,"remaining_time":0.1111694729},
{"learn":[0.01171764126],"iteration":947,"passed_time":1.987430694,"remaining_time":0.1090151858},
{"learn":[0.01170175735],"iteration":948,"passed_time":1.988561286,"remaining_time":0.1068668341},
{"learn":[0.01167434599],"iteration":949,"passed_time":1.98957641,"remaining_time":0.1047145479},
{"learn":[0.01165612732],"iteration":950,"passed_time":1.990578797,"remaining_time":0.1025639969},
{"learn":[0.01163828179],"iteration":951,"passed_time":1.991815135,"remaining_time":0.1004276539},
{"learn":[0.0116210827],"iteration":952,"passed_time":1.99288485,"remaining_time":0.0982849821},
{"learn":[0.01160757328],"iteration":953,"passed_time":1.993995545,"remaining_time":0.09614653574},
{"learn":[0.01159836994],"iteration":954,"passed_time":1.995168488,"remaining_time":0.09401317482},
{"learn":[0.01157831758],"iteration":955,"passed_time":1.996287159,"remaining_time":0.09187932531},
{"learn":[0.01156092853],"iteration":956,"passed_time":1.997381473,"remaining_time":0.08974650296},
{"learn":[0.01153106418],"iteration":957,"passed_time":1.998559885,"remaining_time":0.08761953567},
{"learn":[0.01151580345],"iteration":958,"passed_time":1.999738329,"remaining_time":0.08549454797},
{"learn":[0.01149419556],"iteration":959,"passed_time":2.000936578,"remaining_time":0.0833723574},
{"learn":[0.0114815429],"iteration":960,"passed_time":2.002002701,"remaining_time":0.08124672772},
{"learn":[0.0114621961],"iteration":961,"passed_time":2.003012841,"remaining_time":0.07912108937},
{"learn":[0.01144624919],"iteration":962,"passed_time":2.004148303,"remaining_time":0.07700258279},
{"learn":[0.01143071322],"iteration":963,"passed_time":2.005294814,"remaining_time":0.07488652833},
{"learn":[0.01141457441],"iteration":964,"passed_time":2.006620499,"remaining_time":0.07277898181},
{"learn":[0.01138877772],"iteration":965,"passed_time":2.008026721,"remaining_time":0.07067588872},
{"learn":[0.01136035357],"iteration":966,"passed_time":2.009400222,"remaining_time":0.06857312031},
{"learn":[0.01134488835],"iteration":967,"passed_time":2.010665377,"remaining_time":0.06646827693},
{"learn":[0.01133295773],"iteration":968,"passed_time":2.011721359,"remaining_time":0.06435847485},
{"learn":[0.01131206024],"iteration":969,"passed_time":2.013170799,"remaining_time":0.06226301439},
{"learn":[0.01128539225],"iteration":970,"passed_time":2.014433794,"remaining_time":0.06016331619},
{"learn":[0.01127046201],"iteration":971,"passed_time":2.015475926,"remaining_time":0.05805897729},
{"learn":[0.01124410319],"iteration":972,"passed_time":2.01657519,"remaining_time":0.05595840714},
{"learn":[0.01122498803],"iteration":973,"passed_time":2.017603172,"remaining_time":0.05385799023},
{"learn":[0.01120820375],"iteration":974,"passed_time":2.018664125,"remaining_time":0.05176061858},
{"learn":[0.01119527972],"iteration":975,"passed_time":2.019687316,"remaining_time":0.0496644422},
{"learn":[0.01118044058],"iteration":976,"passed_time":2.020831442,"remaining_time":0.04757330927},
{"learn":[0.011168666],"iteration":977,"passed_time":2.021837918,"remaining_time":0.04548101655},
{"learn":[0.01115243609],"iteration":978,"passed_time":2.022994059,"remaining_time":0.04339415244},
{"learn":[0.01111917864],"iteration":979,"passed_time":2.024146497,"remaining_time":0.04130911219},
{"learn":[0.01110093574],"iteration":980,"passed_time":2.025337228,"remaining_time":0.03922671491},
{"learn":[0.01108889367],"iteration":981,"passed_time":2.026487301,"remaining_time":0.03714538841},
{"learn":[0.01107557033],"iteration":982,"passed_time":2.027564789,"remaining_time":0.03506470134},
{"learn":[0.0110584701],"iteration":983,"passed_time":2.028916419,"remaining_time":0.03299051088},
{"learn":[0.0110492086],"iteration":984,"passed_time":2.030065039,"remaining_time":0.03091469603},
{"learn":[0.01103046851],"iteration":985,"passed_time":2.031127894,"remaining_time":0.02883954414},
{"learn":[0.01101592304],"iteration":986,"passed_time":2.032183943,"remaining_time":0.02676635386},
{"learn":[0.01099968732],"iteration":987,"passed_time":2.033449118,"remaining_time":0.02469776256},
{"learn":[0.01097672935],"iteration":988,"passed_time":2.034645711,"remaining_time":0.02263003318},
{"learn":[0.01095514957],"iteration":989,"passed_time":2.035689607,"remaining_time":0.02056252128},
{"learn":[0.01094380239],"iteration":990,"passed_time":2.036697275,"remaining_time":0.01849674619},
{"learn":[0.01092737186],"iteration":991,"passed_time":2.037720757,"remaining_time":0.01643323191},
{"learn":[0.01090612741],"iteration":992,"passed_time":2.038768642,"remaining_time":0.01437198438},
{"learn":[0.0108962563],"iteration":993,"passed_time":2.03984147,"remaining_time":0.01231292638},
{"learn":[0.01087112349],"iteration":994,"passed_time":2.040850631,"remaining_time":0.01025553081},
{"learn":[0.01085007869],"iteration":995,"passed_time":2.041861015,"remaining_time":0.008200245041},
{"learn":[0.01083432077],"iteration":996,"passed_time":2.042935406,"remaining_time":0.006147247963},
{"learn":[0.01081529187],"iteration":997,"passed_time":2.044166696,"remaining_time":0.004096526444},
{"learn":[0.01080069503],"iteration":998,"passed_time":2.0452892,"remaining_time":0.002047336536},
{"learn":[0.0107801891],"iteration":999,"passed_time":2.048679101,"remaining_time":0}
]}